{
    "tocrawl": {},
    "visited": {
        "https://www.mcdartshop.nl/": -1
    },
    "product": {},
    "results": [
        {
            "crawled-url": "https://www.mcdartshop.nl/",
            "referrer-policy": "",
            "request-leakage": [
                {
                    "request-url": "https://www.google-analytics.com/j/collect?v=1&_v=j96&a=1217357263&t=pageview&_s=1&dl=https%3A%2F%2Fwww.mcdartshop.nl%2F&ul=en-gb&de=UTF-8&dt=Online%20Dartshop%20%7C%20Mcdartshop.nl%20%7C%20Dartwinkel%20-%20Mcdartshop.nl&sd=24-bit&sr=800x600&vp=1440x812&je=0&_u=YEBAAUABAAAAAC~&jid=1747609386&gjid=1739277965&cid=279176216.1639584477&tid=UA-111424666-1&_gid=1066015546.1639584477&_r=1&gtm=2ouc10&z=323531074",
                    "part-found": "source-percent",
                    "encoding": "none"
                },
                {
                    "request-url": "https://www.facebook.com/tr/?id=1834643290198831&ev=PageView&dl=https%3A%2F%2Fwww.mcdartshop.nl%2F&rl=&if=false&ts=1639584476966&sw=800&sh=600&v=2.9.48&r=stable&ec=0&o=30&fbp=fb.1.1639584476964.1423921038&it=1639584476736&coo=false&rqm=GET",
                    "part-found": "source-percent",
                    "encoding": "none"
                }
            ]
        }
    ]
}