{
  "initialUrl": "https://www.kipling.com/nl-nl/allie-black-mist-ki4363x4600-999.html",
  "finalUrl": "https://www.kipling.com/nl-nl/allie-black-mist-ki4363x4600-999.html",
  "timeout": false,
  "testStarted": 1640134776909,
  "testFinished": 1640134792885,
  "data": {
    "links": "Internal links were collected and saved to data/Corpus-Head-crawl/data.kipling.com/links.www.kipling.com_c74d.json",
    "requests": [
      {
        "url": "https://www.kipling.com/nl-nl/allie-black-mist-ki4363x4600-999.html",
        "method": "GET",
        "type": "Document",
        "referrerPolicy": "strict-origin-when-cross-origin",
        "status": 200,
        "size": 34967,
        "remoteIPAddress": "23.222.38.47",
        "responseHeaders": {
          "cache-control": "no-store, no-cache, must-revalidate, max-age=0",
          "expires": "-1",
          "pragma": "no-cache"
        },
        "responseBodyHash": "438e75628118bbf8c1a0cbe5fc9a577a74c099e6db1e373cc45cc284fa6f2f41",
        "initiators": [],
        "time": 1.7316939999873284
      },
      {
        "url": "https://www.kipling.com/static/version1636522060/frontend/Vf/kipling/nl_NL/fonts/opensans/light/opensans-300.woff2",
        "method": "GET",
        "type": "Font",
        "referrerPolicy": "strict-origin-when-cross-origin",
        "referer": "https://www.kipling.com/nl-nl/allie-black-mist-ki4363x4600-999.html",
        "status": 200,
        "size": 17670,
        "remoteIPAddress": "23.222.38.47",
        "responseHeaders": {
          "cache-control": "max-age=31536000, public",
          "etag": "\"618b60b2-441c\"",
          "expires": "Sat, 26 Nov 2022 06:52:26 GMT"
        },
        "responseBodyHash": "d01ad7eb52ddb53a8cbb67a47d52c9dc7b9cf96e140c995f2931eea2d1f17d8f",
        "initiators": [
          "https://www.kipling.com/nl-nl/allie-black-mist-ki4363x4600-999.html"
        ],
        "time": 0.030827000009594485
      },
      {
        "url": "https://www.kipling.com/static/version1636522060/frontend/Vf/kipling/nl_NL/fonts/opensans/regular/opensans-400.woff2",
        "method": "GET",
        "type": "Font",
        "referrerPolicy": "strict-origin-when-cross-origin",
        "referer": "https://www.kipling.com/nl-nl/allie-black-mist-ki4363x4600-999.html",
        "status": 200,
        "size": 18082,
        "remoteIPAddress": "23.222.38.47",
        "responseHeaders": {
          "cache-control": "max-age=31536000, public",
          "etag": "\"618b60b2-45b8\"",
          "expires": "Sat, 26 Nov 2022 06:51:38 GMT"
        },
        "responseBodyHash": "7b5496c41e154198e8981c3a2da04c08f0ebfc6662ac81a75daaee9394eedc49",
        "initiators": [
          "https://www.kipling.com/nl-nl/allie-black-mist-ki4363x4600-999.html"
        ],
        "time": 0.06109499998274259
      },
      {
        "url": "https://www.kipling.com/static/version1636522060/frontend/Vf/kipling/nl_NL/fonts/opensans/semibold/opensans-600.woff2",
        "method": "GET",
        "type": "Font",
        "referrerPolicy": "strict-origin-when-cross-origin",
        "referer": "https://www.kipling.com/nl-nl/allie-black-mist-ki4363x4600-999.html",
        "status": 200,
        "size": 18214,
        "remoteIPAddress": "23.222.38.47",
        "responseHeaders": {
          "cache-control": "max-age=31536000, public",
          "etag": "\"618b60b2-463c\"",
          "expires": "Sat, 26 Nov 2022 06:52:19 GMT"
        },
        "responseBodyHash": "f0a5f635b99389574881dcb000aaa0278e3a5ad73856cfba345142a1112c9296",
        "initiators": [
          "https://www.kipling.com/nl-nl/allie-black-mist-ki4363x4600-999.html"
        ],
        "time": 0.08706699998583645
      },
      {
        "url": "https://www.kipling.com/static/version1636522060/frontend/Vf/kipling/nl_NL/fonts/opensans/bold/opensans-700.woff2",
        "method": "GET",
        "type": "Font",
        "referrerPolicy": "strict-origin-when-cross-origin",
        "referer": "https://www.kipling.com/nl-nl/allie-black-mist-ki4363x4600-999.html",
        "status": 200,
        "size": 17902,
        "remoteIPAddress": "23.222.38.47",
        "responseHeaders": {
          "cache-control": "max-age=31536000, public",
          "etag": "\"618b60b2-4504\"",
          "expires": "Sat, 26 Nov 2022 06:52:21 GMT"
        },
        "responseBodyHash": "67476631488592012ad893355c4ef7b152f89d426391934f324b2dfeb3a53a1d",
        "initiators": [
          "https://www.kipling.com/nl-nl/allie-black-mist-ki4363x4600-999.html"
        ],
        "time": 0.10026900001685135
      },
      {
        "url": "https://www.kipling.com/static/version1636522060/frontend/Vf/kipling/nl_NL/fonts/Luma-Icons.woff2",
        "method": "GET",
        "type": "Font",
        "referrerPolicy": "strict-origin-when-cross-origin",
        "referer": "https://www.kipling.com/nl-nl/allie-black-mist-ki4363x4600-999.html",
        "status": 200,
        "size": 3468,
        "remoteIPAddress": "23.222.38.47",
        "responseHeaders": {
          "cache-control": "max-age=31536000, public",
          "etag": "\"618b60b2-cc8\"",
          "expires": "Sat, 26 Nov 2022 06:52:15 GMT"
        },
        "responseBodyHash": "357da52cfcec8749602d70fc75c0b2feae1d823d57b43c7ec0946113394733da",
        "initiators": [
          "https://www.kipling.com/nl-nl/allie-black-mist-ki4363x4600-999.html"
        ],
        "time": 0.11067200000979938
      },
      {
        "url": "https://www.kipling.com/static/version1636522060/frontend/Vf/kipling/nl_NL/Vf_Amplience/css/amplience.min.css",
        "method": "GET",
        "type": "Stylesheet",
        "referrerPolicy": "strict-origin-when-cross-origin",
        "referer": "https://www.kipling.com/nl-nl/allie-black-mist-ki4363x4600-999.html",
        "status": 200,
        "size": 19169,
        "remoteIPAddress": "23.222.38.47",
        "responseHeaders": {
          "cache-control": "max-age=31536000, public",
          "etag": "W/\"618b60b5-3a410\"",
          "expires": "Sat, 26 Nov 2022 06:52:15 GMT"
        },
        "responseBodyHash": "20d1f4386f87c17c7dbf298ba2e05ad3477670e782115d9903d890cc254ef5f9",
        "initiators": [
          "https://www.kipling.com/nl-nl/allie-black-mist-ki4363x4600-999.html"
        ],
        "time": 0.10909099999116734
      },
      {
        "url": "https://www.kipling.com/static/version1636522060/_cache/merged/b2dea1ece461dcb9ca9ce0a800b92a00.min.css",
        "method": "GET",
        "type": "Stylesheet",
        "referrerPolicy": "strict-origin-when-cross-origin",
        "referer": "https://www.kipling.com/nl-nl/allie-black-mist-ki4363x4600-999.html",
        "status": 200,
        "size": 99324,
        "remoteIPAddress": "23.222.38.47",
        "responseHeaders": {
          "cache-control": "max-age=31536000, public",
          "etag": "W/\"618b6500-f1686\"",
          "expires": "Sat, 26 Nov 2022 06:52:21 GMT"
        },
        "responseBodyHash": "84b9fcfde9b99c7c681f3da25c30cccd3383e79118420ae9d004a23e4ff0f8a3",
        "initiators": [
          "https://www.kipling.com/nl-nl/allie-black-mist-ki4363x4600-999.html"
        ],
        "time": 0.1577910000050906
      },
      {
        "url": "https://www.kipling.com/static/version1636522060/frontend/Vf/kipling/nl_NL/css/styles-l.min.css",
        "method": "GET",
        "type": "Stylesheet",
        "referrerPolicy": "strict-origin-when-cross-origin",
        "referer": "https://www.kipling.com/nl-nl/allie-black-mist-ki4363x4600-999.html",
        "status": 200,
        "size": 21253,
        "remoteIPAddress": "23.222.38.47",
        "responseHeaders": {
          "cache-control": "max-age=31536000, public",
          "etag": "W/\"618b60b4-2709e\"",
          "expires": "Sat, 26 Nov 2022 06:52:21 GMT"
        },
        "responseBodyHash": "fa895da074d5728a00d791482aea84e1945b0c6457e56c1ec8c4754c2f937e0c",
        "initiators": [
          "https://www.kipling.com/nl-nl/allie-black-mist-ki4363x4600-999.html"
        ],
        "time": 0.11380099999951199
      },
      {
        "url": "https://www.kipling.com/media/wysiwyg/usp_icons/usp_free_delivery_new.png",
        "method": "GET",
        "type": "Image",
        "referrerPolicy": "strict-origin-when-cross-origin",
        "referer": "https://www.kipling.com/nl-nl/allie-black-mist-ki4363x4600-999.html",
        "status": 200,
        "size": 5986,
        "remoteIPAddress": "23.222.38.47",
        "responseHeaders": {
          "cache-control": "max-age=31536000, public",
          "etag": "\"5f71f4db-169c\"",
          "expires": "Sun, 27 Nov 2022 03:49:53 GMT"
        },
        "responseBodyHash": "7bba5020f53e86899c274987631a8d41ae09a426044a767d9f43249b06c56216",
        "initiators": [
          "https://www.kipling.com/nl-nl/allie-black-mist-ki4363x4600-999.html"
        ],
        "time": 0.11592099998961203
      },
      {
        "url": "https://www.kipling.com/media/wysiwyg/usp_icons/usp_secure_payment.png",
        "method": "GET",
        "type": "Image",
        "referrerPolicy": "strict-origin-when-cross-origin",
        "referer": "https://www.kipling.com/nl-nl/allie-black-mist-ki4363x4600-999.html",
        "status": 200,
        "size": 8217,
        "remoteIPAddress": "23.222.38.47",
        "responseHeaders": {
          "cache-control": "max-age=31536000, public",
          "etag": "\"5d8a084e-1f4a\"",
          "expires": "Sun, 27 Nov 2022 03:49:53 GMT"
        },
        "responseBodyHash": "e518d725b689e9d518ae8ac261eda518678e7ae39793df4cd1b4264a07f273f9",
        "initiators": [
          "https://www.kipling.com/nl-nl/allie-black-mist-ki4363x4600-999.html"
        ],
        "time": 0.11613400001078844
      },
      {
        "url": "https://www.kipling.com/static/version1636522060/frontend/Vf/kipling/nl_NL/images/logo.png",
        "method": "GET",
        "type": "Image",
        "referrerPolicy": "strict-origin-when-cross-origin",
        "referer": "https://www.kipling.com/nl-nl/allie-black-mist-ki4363x4600-999.html",
        "status": 200,
        "size": 4548,
        "remoteIPAddress": "23.222.38.47",
        "responseHeaders": {
          "cache-control": "max-age=31536000, public",
          "etag": "\"618b60b4-10ff\"",
          "expires": "Sun, 27 Nov 2022 00:09:39 GMT"
        },
        "responseBodyHash": "fa1b55d77cb8b5dd329258b14e49e8f47aeca3e4d2767e2edea1e57e2bc5d0a8",
        "initiators": [
          "https://www.kipling.com/nl-nl/allie-black-mist-ki4363x4600-999.html"
        ],
        "time": 0.11744400000316091
      },
      {
        "url": "https://www.kipling.com/static/version1636522060/frontend/Vf/kipling/nl_NL/css/print.min.css",
        "method": "GET",
        "type": "Stylesheet",
        "referrerPolicy": "strict-origin-when-cross-origin",
        "referer": "https://www.kipling.com/nl-nl/allie-black-mist-ki4363x4600-999.html",
        "status": 200,
        "size": 606,
        "remoteIPAddress": "23.222.38.47",
        "responseHeaders": {
          "cache-control": "max-age=31536000, public",
          "etag": "W/\"618b60b4-4a7\"",
          "expires": "Sat, 26 Nov 2022 06:52:31 GMT"
        },
        "responseBodyHash": "1325fbbd83887b4b56f821607648184ecaf3f1ee716363657064055fece579b4",
        "initiators": [
          "https://www.kipling.com/nl-nl/allie-black-mist-ki4363x4600-999.html"
        ],
        "time": 0.11801999999443069
      },
      {
        "url": "https://www.kipling.com/static/version1636522060/frontend/Vf/kipling/nl_NL/magepack/bundle-common.min.js",
        "method": "GET",
        "type": "Other",
        "referrerPolicy": "strict-origin-when-cross-origin",
        "referer": "https://www.kipling.com/nl-nl/allie-black-mist-ki4363x4600-999.html",
        "status": 200,
        "size": 239270,
        "remoteIPAddress": "23.222.38.47",
        "responseHeaders": {
          "cache-control": "max-age=31536000, public",
          "etag": "W/\"618b60b6-10360c\"",
          "expires": "Sat, 26 Nov 2022 23:23:12 GMT"
        },
        "responseBodyHash": "e3b0c44298fc1c149afbf4c8996fb92427ae41e4649b934ca495991b7852b855",
        "initiators": [
          "https://www.kipling.com/nl-nl/allie-black-mist-ki4363x4600-999.html"
        ],
        "time": 0.16013100001146086
      },
      {
        "url": "https://www.kipling.com/static/version1636522060/frontend/Vf/kipling/nl_NL/magepack/bundle-product.min.js",
        "method": "GET",
        "type": "Other",
        "referrerPolicy": "strict-origin-when-cross-origin",
        "referer": "https://www.kipling.com/nl-nl/allie-black-mist-ki4363x4600-999.html",
        "status": 200,
        "size": 33920,
        "remoteIPAddress": "23.222.38.47",
        "responseHeaders": {
          "cache-control": "max-age=31536000, public",
          "etag": "W/\"618b60b6-1e801\"",
          "expires": "Sat, 26 Nov 2022 06:53:36 GMT"
        },
        "responseBodyHash": "e3b0c44298fc1c149afbf4c8996fb92427ae41e4649b934ca495991b7852b855",
        "initiators": [
          "https://www.kipling.com/nl-nl/allie-black-mist-ki4363x4600-999.html"
        ],
        "time": 0.1332389999879524
      },
      {
        "url": "https://www.kipling.com/static/version1636522060/frontend/Vf/kipling/nl_NL/Vf_KiplingProductIcons/images/lightweight.svg",
        "method": "GET",
        "type": "Image",
        "referrerPolicy": "strict-origin-when-cross-origin",
        "referer": "https://www.kipling.com/nl-nl/allie-black-mist-ki4363x4600-999.html",
        "status": 200,
        "size": 791,
        "remoteIPAddress": "23.222.38.47",
        "responseHeaders": {
          "cache-control": "max-age=31536000, public",
          "etag": "W/\"618b60b3-50d\"",
          "expires": "Sat, 26 Nov 2022 17:57:00 GMT"
        },
        "responseBodyHash": "a6d49ce3e261d1d2ed1b4a1354b4240cac50a15859159071cb19f630dabc0371",
        "initiators": [
          "https://www.kipling.com/nl-nl/allie-black-mist-ki4363x4600-999.html"
        ],
        "time": 0.12291499998536892
      },
      {
        "url": "https://www.kipling.com/static/version1636522060/frontend/Vf/kipling/nl_NL/Vf_KiplingProductIcons/images/water_repellent.svg",
        "method": "GET",
        "type": "Image",
        "referrerPolicy": "strict-origin-when-cross-origin",
        "referer": "https://www.kipling.com/nl-nl/allie-black-mist-ki4363x4600-999.html",
        "status": 200,
        "size": 755,
        "remoteIPAddress": "23.222.38.47",
        "responseHeaders": {
          "cache-control": "max-age=31536000, public",
          "etag": "W/\"618b60b3-50c\"",
          "expires": "Sat, 26 Nov 2022 16:30:02 GMT"
        },
        "responseBodyHash": "79cdebbf14950fe4b9ad8644e33b32e30f86da3f50e06a7979c0254c8a5008fb",
        "initiators": [
          "https://www.kipling.com/nl-nl/allie-black-mist-ki4363x4600-999.html"
        ],
        "time": 0.12349900000845082
      },
      {
        "url": "https://www.kipling.com/static/version1636522060/_cache/merged/33c3a92e596bcb0a6527f8461165bcad.min.js",
        "method": "GET",
        "type": "Script",
        "referrerPolicy": "strict-origin-when-cross-origin",
        "referer": "https://www.kipling.com/nl-nl/allie-black-mist-ki4363x4600-999.html",
        "status": 200,
        "size": 21608,
        "remoteIPAddress": "23.222.38.47",
        "responseHeaders": {
          "cache-control": "max-age=31536000, public",
          "etag": "W/\"618b64ff-16f54\"",
          "expires": "Sat, 26 Nov 2022 06:52:18 GMT"
        },
        "responseBodyHash": "6297852ae36fd32d98634fca48004711ed92abdda947a82a0688b9627e1e78fa",
        "initiators": [
          "https://www.kipling.com/nl-nl/allie-black-mist-ki4363x4600-999.html"
        ],
        "time": 0.11063599999761209
      },
      {
        "url": "https://www.datadoghq-browser-agent.com/datadog-rum.js",
        "method": "GET",
        "type": "Script",
        "referrerPolicy": "strict-origin-when-cross-origin",
        "referer": "https://www.kipling.com/",
        "status": 200,
        "size": 22270,
        "remoteIPAddress": "65.9.76.214",
        "responseHeaders": {
          "cache-control": "max-age=14400, s-maxage=60",
          "etag": "W/\"6f16bc452a225d7da116aa4c430872f8\""
        },
        "responseBodyHash": "54cc471e6d75456315e6685c7af0dcdee292fddb9c31d4b7b0c5f75eb668d35c",
        "initiators": [
          "https://www.kipling.com/nl-nl/allie-black-mist-ki4363x4600-999.html"
        ],
        "time": 0.016218000004300848
      },
      {
        "url": "https://ui.powerreviews.com/stable/4.1/ui.js",
        "method": "GET",
        "type": "Script",
        "referrerPolicy": "strict-origin-when-cross-origin",
        "referer": "https://www.kipling.com/",
        "status": 200,
        "size": 3526,
        "remoteIPAddress": "65.9.83.58",
        "responseHeaders": {
          "access-control-allow-origin": "*",
          "cache-control": "max-age=1800,s-maxage=604800000",
          "etag": "W/\"518514d8f93fa355236e9a59fe9115d2\""
        },
        "responseBodyHash": "ac69b64bb0491f4fa493d3e49aac51012ed5662ff164ac10066764d92c9f8359",
        "initiators": [
          "https://www.kipling.com/nl-nl/allie-black-mist-ki4363x4600-999.html"
        ],
        "time": 0.0298659999971278
      },
      {
        "url": "https://www.kipling.com/static/version1636522060/frontend/Vf/kipling/nl_NL/images/sprite.png",
        "method": "GET",
        "type": "Image",
        "referrerPolicy": "strict-origin-when-cross-origin",
        "referer": "https://www.kipling.com/static/version1636522060/_cache/merged/b2dea1ece461dcb9ca9ce0a800b92a00.min.css",
        "status": 200,
        "size": 75739,
        "remoteIPAddress": "23.222.38.47",
        "responseHeaders": {
          "cache-control": "max-age=31536000, public",
          "etag": "\"618b60b4-1267b\"",
          "expires": "Sun, 27 Nov 2022 01:29:59 GMT"
        },
        "responseBodyHash": "bb5426cfaae38f98931a12251cfa3b196871bacb0d7ab7d204bd85910b368589",
        "initiators": [
          "https://www.kipling.com/static/version1636522060/_cache/merged/b2dea1ece461dcb9ca9ce0a800b92a00.min.css"
        ],
        "time": 0.006896000006236136
      },
      {
        "url": "https://www.kipling.com/static/version1636522060/frontend/Vf/kipling/nl_NL/fonts/kipling_bold-webfont.woff2",
        "method": "GET",
        "type": "Font",
        "referrerPolicy": "strict-origin-when-cross-origin",
        "referer": "https://www.kipling.com/static/version1636522060/_cache/merged/b2dea1ece461dcb9ca9ce0a800b92a00.min.css",
        "status": 200,
        "size": 23399,
        "remoteIPAddress": "23.222.38.47",
        "responseHeaders": {
          "cache-control": "max-age=31536000, public",
          "etag": "\"618b60b2-5a74\"",
          "expires": "Sat, 26 Nov 2022 22:02:07 GMT"
        },
        "responseBodyHash": "5510931303d4bb6f2baef535bd51a97199517038405230b4fe18f4519bc9d933",
        "initiators": [
          "https://www.kipling.com/static/version1636522060/_cache/merged/b2dea1ece461dcb9ca9ce0a800b92a00.min.css"
        ],
        "time": 0.18553899999824353
      },
      {
        "url": "https://www.kipling.com/static/version1636522060/frontend/Vf/kipling/nl_NL/fonts/kipling_regular-webfont.woff2",
        "method": "GET",
        "type": "Font",
        "referrerPolicy": "strict-origin-when-cross-origin",
        "referer": "https://www.kipling.com/static/version1636522060/_cache/merged/b2dea1ece461dcb9ca9ce0a800b92a00.min.css",
        "status": 200,
        "size": 23719,
        "remoteIPAddress": "23.222.38.47",
        "responseHeaders": {
          "cache-control": "max-age=31536000, public",
          "etag": "\"618b60b2-5bb4\"",
          "expires": "Sat, 26 Nov 2022 22:51:51 GMT"
        },
        "responseBodyHash": "c6d1f83626281024f450e43948ffd4ad7c644aa97b255562a8b33ed9ff330fc7",
        "initiators": [
          "https://www.kipling.com/static/version1636522060/_cache/merged/b2dea1ece461dcb9ca9ce0a800b92a00.min.css"
        ],
        "time": 0.20006000000284985
      },
      {
        "url": "https://www.kipling.com/static/version1636522060/frontend/Vf/kipling/nl_NL/fonts/icons/Kipling-Icons.woff2",
        "method": "GET",
        "type": "Font",
        "referrerPolicy": "strict-origin-when-cross-origin",
        "referer": "https://www.kipling.com/static/version1636522060/_cache/merged/b2dea1ece461dcb9ca9ce0a800b92a00.min.css",
        "status": 200,
        "size": 5434,
        "remoteIPAddress": "23.222.38.47",
        "responseHeaders": {
          "cache-control": "max-age=31536000, public",
          "etag": "\"618b60b2-146c\"",
          "expires": "Sat, 26 Nov 2022 07:13:47 GMT"
        },
        "responseBodyHash": "e3ff0650b7f9f8b837553275c1a3a38987311429a7ec89756e377e2644a878ed",
        "initiators": [
          "https://www.kipling.com/static/version1636522060/_cache/merged/b2dea1ece461dcb9ca9ce0a800b92a00.min.css"
        ],
        "time": 0.20182099999510683
      },
      {
        "url": "https://www.kipling.com/media/catalog/product/cache/9d7c896cfb4307ce2143e4873e3c9dcb/K/I/KI4363X4600_999_1_1.jpg",
        "method": "GET",
        "type": "Image",
        "referrerPolicy": "strict-origin-when-cross-origin",
        "referer": "https://www.kipling.com/nl-nl/allie-black-mist-ki4363x4600-999.html",
        "status": 200,
        "size": 111293,
        "remoteIPAddress": "23.222.38.47",
        "responseHeaders": {
          "cache-control": "max-age=31536000, public",
          "etag": "\"6077454f-1b109\"",
          "expires": "Sun, 27 Nov 2022 08:34:58 GMT"
        },
        "responseBodyHash": "c6e1e448ad6feff1cab9ed01ea394bcc96da4f21cffe38b491fdf011063e6e7c",
        "initiators": [
          "https://www.kipling.com/nl-nl/allie-black-mist-ki4363x4600-999.html"
        ],
        "time": 0.01957500001299195
      },
      {
        "url": "https://www.kipling.com/media/catalog/product/cache/9318b355b9f613057787af222929d3a8/K/I/KI4363X4600_999_1_1.jpg",
        "method": "GET",
        "type": "Image",
        "referrerPolicy": "strict-origin-when-cross-origin",
        "referer": "https://www.kipling.com/nl-nl/allie-black-mist-ki4363x4600-999.html",
        "status": 200,
        "size": 26670,
        "remoteIPAddress": "23.222.38.47",
        "responseHeaders": {
          "cache-control": "max-age=31536000, public",
          "etag": "\"60774552-6731\"",
          "expires": "Sat, 26 Nov 2022 06:52:03 GMT"
        },
        "responseBodyHash": "1843c53a761d5d8882399f18764728afbafde5177528ef0d49f88b364e9b8f9a",
        "initiators": [
          "https://www.kipling.com/nl-nl/allie-black-mist-ki4363x4600-999.html"
        ],
        "time": 0.01648600000771694
      },
      {
        "url": "https://www.kipling.com/media/catalog/product/cache/9318b355b9f613057787af222929d3a8/K/I/KI4363O7600_999_1_1.jpg",
        "method": "GET",
        "type": "Image",
        "referrerPolicy": "strict-origin-when-cross-origin",
        "referer": "https://www.kipling.com/nl-nl/allie-black-mist-ki4363x4600-999.html",
        "status": 200,
        "size": 29398,
        "remoteIPAddress": "23.222.38.47",
        "responseHeaders": {
          "cache-control": "max-age=31536000, public",
          "etag": "\"6077454a-71d0\"",
          "expires": "Sun, 27 Nov 2022 01:26:12 GMT"
        },
        "responseBodyHash": "0b967690c7d4a1c45188569ce9d59bc64fc4f26f8b32f339a28c9ce1d6e85f99",
        "initiators": [
          "https://www.kipling.com/nl-nl/allie-black-mist-ki4363x4600-999.html"
        ],
        "time": 0.01753499999176711
      },
      {
        "url": "https://www.kipling.com/media/catalog/product/cache/915d7703cf5ac84bc6e374994acf50e0/k/i/ki419276m00_999_1.jpg",
        "method": "GET",
        "type": "Image",
        "referrerPolicy": "strict-origin-when-cross-origin",
        "referer": "https://www.kipling.com/nl-nl/allie-black-mist-ki4363x4600-999.html",
        "status": 200,
        "size": 3179,
        "remoteIPAddress": "23.222.38.47",
        "responseHeaders": {
          "cache-control": "max-age=31536000, public",
          "etag": "\"61010c74-baf\"",
          "expires": "Sat, 26 Nov 2022 07:08:32 GMT"
        },
        "responseBodyHash": "f0fea5345b72c57e3884b72c00bbd1842dd096c2ee249fdc0690410d2ca358ef",
        "initiators": [
          "https://www.kipling.com/nl-nl/allie-black-mist-ki4363x4600-999.html"
        ],
        "time": 0.01802099999622442
      },
      {
        "url": "https://www.kipling.com/media/catalog/product/cache/915d7703cf5ac84bc6e374994acf50e0/K/I/KI724378S00_999_1_1.jpg",
        "method": "GET",
        "type": "Image",
        "referrerPolicy": "strict-origin-when-cross-origin",
        "referer": "https://www.kipling.com/nl-nl/allie-black-mist-ki4363x4600-999.html",
        "status": 200,
        "size": 3115,
        "remoteIPAddress": "23.222.38.47",
        "responseHeaders": {
          "cache-control": "max-age=31536000, public",
          "etag": "\"5f3e48fd-b6e\"",
          "expires": "Sat, 26 Nov 2022 22:09:31 GMT"
        },
        "responseBodyHash": "ea0b2387fceff24b4f553c9538a0a72536c35c562b8047c45130101975b4608e",
        "initiators": [
          "https://www.kipling.com/nl-nl/allie-black-mist-ki4363x4600-999.html"
        ],
        "time": 0.018609999999171123
      },
      {
        "url": "https://www.kipling.com/media/catalog/product/cache/915d7703cf5ac84bc6e374994acf50e0/K/I/KI362078S00_999_1_1.jpg",
        "method": "GET",
        "type": "Image",
        "referrerPolicy": "strict-origin-when-cross-origin",
        "referer": "https://www.kipling.com/nl-nl/allie-black-mist-ki4363x4600-999.html",
        "status": 200,
        "size": 3263,
        "remoteIPAddress": "23.222.38.47",
        "responseHeaders": {
          "cache-control": "max-age=31536000, public",
          "etag": "\"5f460c8b-c03\"",
          "expires": "Sun, 27 Nov 2022 01:21:52 GMT"
        },
        "responseBodyHash": "18f8bb55dc5d4f0dd06df7da35ba81ce70cae58a483838719ec6e1b04ae0ce99",
        "initiators": [
          "https://www.kipling.com/nl-nl/allie-black-mist-ki4363x4600-999.html"
        ],
        "time": 0.0192490000044927
      },
      {
        "url": "https://www.kipling.com/media/catalog/product/cache/915d7703cf5ac84bc6e374994acf50e0/import/item/1/K21092J9900%20999.jpg",
        "method": "GET",
        "type": "Image",
        "referrerPolicy": "strict-origin-when-cross-origin",
        "referer": "https://www.kipling.com/nl-nl/allie-black-mist-ki4363x4600-999.html",
        "status": 200,
        "size": 2849,
        "remoteIPAddress": "23.222.38.47",
        "responseHeaders": {
          "cache-control": "max-age=31536000, public",
          "etag": "\"61c0cb5e-a65\"",
          "expires": "Wed, 21 Dec 2022 08:45:29 GMT"
        },
        "responseBodyHash": "733d66bd337313dd65f702deb4e5b13f532f1b04cbd43b7be331f15f17a113ac",
        "initiators": [
          "https://www.kipling.com/nl-nl/allie-black-mist-ki4363x4600-999.html"
        ],
        "time": 0.020758999977260828
      },
      {
        "url": "https://www.kipling.com/media/catalog/product/cache/915d7703cf5ac84bc6e374994acf50e0/K/1/K1537189L00_999_1_1.jpg",
        "method": "GET",
        "type": "Image",
        "referrerPolicy": "strict-origin-when-cross-origin",
        "referer": "https://www.kipling.com/nl-nl/allie-black-mist-ki4363x4600-999.html",
        "status": 200,
        "size": 2845,
        "remoteIPAddress": "23.222.38.47",
        "responseHeaders": {
          "cache-control": "max-age=31536000, public",
          "etag": "\"607743b1-a61\"",
          "expires": "Sun, 27 Nov 2022 05:25:45 GMT"
        },
        "responseBodyHash": "0d5f41a2527d7125d13eb1c9e43df3a5c149b894f2e79a7a3fd2a08079f9fc84",
        "initiators": [
          "https://www.kipling.com/nl-nl/allie-black-mist-ki4363x4600-999.html"
        ],
        "time": 0.022488999995402992
      },
      {
        "url": "https://www.kipling.com/media/catalog/product/cache/915d7703cf5ac84bc6e374994acf50e0/K/I/KI44542CP00_999_1_1.jpg",
        "method": "GET",
        "type": "Image",
        "referrerPolicy": "strict-origin-when-cross-origin",
        "referer": "https://www.kipling.com/nl-nl/allie-black-mist-ki4363x4600-999.html",
        "status": 200,
        "size": 2870,
        "remoteIPAddress": "23.222.38.47",
        "responseHeaders": {
          "cache-control": "max-age=31536000, public",
          "etag": "\"60774561-a7a\"",
          "expires": "Sat, 26 Nov 2022 22:09:31 GMT"
        },
        "responseBodyHash": "5e550519dd60bf19c29a1e678f356f76193168cf389626a54938f350207a6db6",
        "initiators": [
          "https://www.kipling.com/nl-nl/allie-black-mist-ki4363x4600-999.html"
        ],
        "time": 0.022915000008651987
      },
      {
        "url": "https://ui.powerreviews.com/tag-builds/10309/4.1/css/styles.css",
        "method": "GET",
        "type": "Stylesheet",
        "referrerPolicy": "strict-origin-when-cross-origin",
        "referer": "https://www.kipling.com/",
        "status": 200,
        "size": 57025,
        "remoteIPAddress": "65.9.83.58",
        "responseHeaders": {
          "access-control-allow-origin": "*",
          "cache-control": "max-age=604800000",
          "etag": "W/\"0ac0f4836f9677725ada5c05821a503f\""
        },
        "responseBodyHash": "2d0a0e1e33c3258af898ca7b5f1da013e02f39c5f1487586219ce816c1fa0191",
        "initiators": [
          "https://ui.powerreviews.com/stable/4.1/ui.js"
        ],
        "time": 0.026133000006666407
      },
      {
        "url": "https://ui.powerreviews.com/tag-builds/10309/4.1/js/chunks/749.js",
        "method": "GET",
        "type": "Script",
        "referrerPolicy": "strict-origin-when-cross-origin",
        "referer": "https://www.kipling.com/",
        "status": 200,
        "size": 714,
        "remoteIPAddress": "65.9.83.58",
        "responseHeaders": {
          "access-control-allow-origin": "*",
          "cache-control": "max-age=604800000",
          "etag": "\"e1371b9b0ef8649f7472026048ac448f\""
        },
        "responseBodyHash": "b3f7440870442c1c91a16d724f8b617dcad32fe51e457387a2cec805d48cd81e",
        "initiators": [
          "https://ui.powerreviews.com/stable/4.1/ui.js"
        ],
        "time": 0.009825000015553087
      },
      {
        "url": "https://ui.powerreviews.com/tag-builds/10309/4.1/js/chunks/288.js",
        "method": "GET",
        "type": "Script",
        "referrerPolicy": "strict-origin-when-cross-origin",
        "referer": "https://www.kipling.com/",
        "status": 200,
        "size": 712,
        "remoteIPAddress": "65.9.83.58",
        "responseHeaders": {
          "access-control-allow-origin": "*",
          "cache-control": "max-age=604800000",
          "etag": "\"61263b8bf06e51eaeae578e209e18efe\""
        },
        "responseBodyHash": "49d94584db42d517f088d83a3b93975538eaca9556f279eef547ccaa468aba84",
        "initiators": [
          "https://ui.powerreviews.com/stable/4.1/ui.js"
        ],
        "time": 0.015272999997250736
      },
      {
        "url": "https://ui.powerreviews.com/tag-builds/10309/4.1/js/chunks/623.js",
        "method": "GET",
        "type": "Script",
        "referrerPolicy": "strict-origin-when-cross-origin",
        "referer": "https://www.kipling.com/",
        "status": 200,
        "size": 56771,
        "remoteIPAddress": "65.9.83.58",
        "responseHeaders": {
          "access-control-allow-origin": "*",
          "cache-control": "max-age=604800000",
          "etag": "W/\"fd24646486a051a9963c61f499b144b9\""
        },
        "responseBodyHash": "160c8bbea48ee9cf94ead23ef42b9aff62a5084b55f3db1f668ae38203e13f9a",
        "initiators": [
          "https://ui.powerreviews.com/stable/4.1/ui.js"
        ],
        "time": 0.026790000003529713
      },
      {
        "url": "https://ui.powerreviews.com/tag-builds/10309/4.1/js/chunks/engine.js",
        "method": "GET",
        "type": "Script",
        "referrerPolicy": "strict-origin-when-cross-origin",
        "referer": "https://www.kipling.com/",
        "status": 200,
        "size": 37889,
        "remoteIPAddress": "65.9.83.58",
        "responseHeaders": {
          "access-control-allow-origin": "*",
          "cache-control": "max-age=604800000",
          "etag": "W/\"40797eb34aef657cfaf4e53c92e368a0\""
        },
        "responseBodyHash": "7542df756ef5babb81633259a8d632bcd18731338eab05a5d00de592ed901013",
        "initiators": [
          "https://ui.powerreviews.com/stable/4.1/ui.js"
        ],
        "time": 0.023483000026317313
      },
      {
        "url": "https://www.kipling.com/static/version1636522060/frontend/Vf/kipling/nl_NL/magepack/bundle-common.min.js",
        "method": "GET",
        "type": "Script",
        "referrerPolicy": "strict-origin-when-cross-origin",
        "referer": "https://www.kipling.com/nl-nl/allie-black-mist-ki4363x4600-999.html",
        "status": 200,
        "size": 0,
        "remoteIPAddress": "23.222.38.47",
        "responseHeaders": {
          "cache-control": "max-age=31536000, public",
          "etag": "W/\"618b60b6-10360c\"",
          "expires": "Sat, 26 Nov 2022 23:23:12 GMT"
        },
        "responseBodyHash": "b607e68811440a76af3e8babbec3506894f045d48364076a480760a747dc464f",
        "initiators": [
          "https://www.kipling.com/static/version1636522060/_cache/merged/33c3a92e596bcb0a6527f8461165bcad.min.js"
        ],
        "time": 0.16933399997651577
      },
      {
        "url": "https://www.kipling.com/static/version1636522060/frontend/Vf/kipling/nl_NL/magepack/bundle-product.min.js",
        "method": "GET",
        "type": "Script",
        "referrerPolicy": "strict-origin-when-cross-origin",
        "referer": "https://www.kipling.com/nl-nl/allie-black-mist-ki4363x4600-999.html",
        "status": 200,
        "size": 0,
        "remoteIPAddress": "23.222.38.47",
        "responseHeaders": {
          "cache-control": "max-age=31536000, public",
          "etag": "W/\"618b60b6-1e801\"",
          "expires": "Sat, 26 Nov 2022 06:53:36 GMT"
        },
        "responseBodyHash": "45bf409417ea860e1d910670201d5b7a7e4275bce40e47d4ffbe30c7965a7f8c",
        "initiators": [
          "https://www.kipling.com/static/version1636522060/_cache/merged/33c3a92e596bcb0a6527f8461165bcad.min.js",
          "https://www.kipling.com/nl-nl/allie-black-mist-ki4363x4600-999.html"
        ],
        "time": 0.022819999983767048
      },
      {
        "url": "https://ui.powerreviews.com/api/m/811778/l/nl_NL/configuration?apikey=b2d323a8-6479-4904-99cc-4209c42534cc",
        "method": "GET",
        "type": "Fetch",
        "referrerPolicy": "strict-origin-when-cross-origin",
        "referer": "https://www.kipling.com/",
        "status": 200,
        "size": 7023,
        "remoteIPAddress": "65.9.83.58",
        "responseHeaders": {
          "access-control-allow-origin": "https://www.kipling.com",
          "cache-control": "max-age=86400, public",
          "etag": "W/\"0f3042fea65fed5bddf6a2f0439891c05\""
        },
        "responseBodyHash": "2d17c3a84d559bf5a5f473349aca487afd453e9582f7446f7c5eadb7bb0e05b9",
        "initiators": [
          "https://www.datadoghq-browser-agent.com/datadog-rum.js",
          "https://ui.powerreviews.com/tag-builds/10309/4.1/js/chunks/engine.js",
          "https://ui.powerreviews.com/tag-builds/10309/4.1/js/chunks/623.js"
        ],
        "time": 0.009906999999657273
      },
      {
        "url": "https://www.kipling.com/static/version1636522060/frontend/Vf/kipling/nl_NL/js/slick-slider.min.js",
        "method": "GET",
        "type": "Script",
        "referrerPolicy": "strict-origin-when-cross-origin",
        "referer": "https://www.kipling.com/nl-nl/allie-black-mist-ki4363x4600-999.html",
        "status": 200,
        "size": 680,
        "remoteIPAddress": "23.222.38.47",
        "responseHeaders": {
          "cache-control": "max-age=31536000, public",
          "etag": "W/\"618b60b2-54d\"",
          "expires": "Sat, 17 Dec 2022 15:52:02 GMT"
        },
        "responseBodyHash": "acb598cdeb103defcfd3f19f5cdab3d87f6b0de7ddf52c0608d21b0e01175d85",
        "initiators": [
          "https://www.kipling.com/static/version1636522060/_cache/merged/33c3a92e596bcb0a6527f8461165bcad.min.js",
          "https://www.kipling.com/static/version1636522060/frontend/Vf/kipling/nl_NL/magepack/bundle-common.min.js"
        ],
        "time": 0.008925999980419874
      },
      {
        "url": "https://www.googletagmanager.com/gtm.js?id=GTM-NCCHW6",
        "method": "GET",
        "type": "Script",
        "referrerPolicy": "strict-origin-when-cross-origin",
        "referer": "https://www.kipling.com/",
        "status": 200,
        "size": 94145,
        "remoteIPAddress": "142.251.39.104",
        "responseHeaders": {
          "access-control-allow-origin": "*",
          "cache-control": "private, max-age=900",
          "expires": "Wed, 22 Dec 2021 00:59:39 GMT"
        },
        "responseBodyHash": "a513cc3ff8b945d8b9837cd9edf93c63feae6c331f3dcf23c64965c9ee71c031",
        "initiators": [
          "https://www.kipling.com/static/version1636522060/frontend/Vf/kipling/nl_NL/magepack/bundle-common.min.js",
          "https://www.kipling.com/static/version1636522060/_cache/merged/33c3a92e596bcb0a6527f8461165bcad.min.js"
        ],
        "time": 0.026149999990593642
      },
      {
        "url": "https://www.kipling.com/nl-nl/vfgeoip/geoIp/index/?uri_path=%2Fnl-nl%2Fallie-black-mist-ki4363x4600-999.html&_=1640134779547",
        "method": "GET",
        "type": "XHR",
        "referrerPolicy": "strict-origin-when-cross-origin",
        "referer": "https://www.kipling.com/nl-nl/allie-black-mist-ki4363x4600-999.html",
        "status": 200,
        "size": 4798,
        "remoteIPAddress": "23.222.38.47",
        "responseHeaders": {
          "cache-control": "no-store, no-cache, must-revalidate, max-age=0",
          "expires": "-1",
          "pragma": "no-cache",
          "set-cookie": "PHPSESSID=3m323m5dr2vvon1nkpe7tgeorh; expires=Wed, 29-Dec-2021 00:59:40 GMT; Max-Age=604800; path=/; domain=www.kipling.com; HttpOnly\nform_key=8Dr9nCD0oY6gM7X6; expires=Wed, 29-Dec-2021 00:59:40 GMT; Max-Age=604800; path=/; domain=www.kipling.com\nak_bmsc=BE04D3BC296EACAC58A1358A4BD7DC4A~000000000000000000000000000000~YAAQdMMTAnubzcx9AQAAtaSm3w6aWwRZBKDT3tPC/NxrXRX115AM9a2fkRBcw3vk0BBysHG0F4w4zaeXi6s+4mXYyJ0GJmYLD+HU5W7a6jWW0bet6QjloogbMrhvccrV+qMrRFwk/XCsb2l2KJPFxJvgSLWqt3GUTy9EvYa7rr167XJ5ZRUn4CVh/QCQCb1+DcNRCOSueJR9D3gynrJGcAX9XG8xCZQ8z04aBoKIyPxO9uCtUtrNjtZnOsCYPmhYvZXBhHR/8EFyTY7vFArQ/SZk+6HYteriV/+DBNj7XV7VBj7WgINrBxrLaBzp4SIcKy4BhhRpx3FioLOCW9Y1ogl+gNjH5X87qnofkqn2zb6ErRGaWEk3wZjbPmZdyklSjnHfP9f2t60KQHzl; Domain=.kipling.com; Path=/; Expires=Wed, 22 Dec 2021 02:59:39 GMT; Max-Age=7199; HttpOnly"
        },
        "responseBodyHash": "4f53cda18c2baa0c0354bb5f9a3ecbe5ed12ab4d8e11ba873c2f11161202b945",
        "initiators": [
          "https://www.datadoghq-browser-agent.com/datadog-rum.js",
          "https://www.kipling.com/static/version1636522060/frontend/Vf/kipling/nl_NL/magepack/bundle-common.min.js",
          "https://www.kipling.com/static/version1636522060/_cache/merged/33c3a92e596bcb0a6527f8461165bcad.min.js"
        ],
        "time": 0.1342690000019502
      },
      {
        "url": "https://display.powerreviews.com/m/811778/l/nl_NL/product/AMIEL/reviews?apikey=b2d323a8-6479-4904-99cc-4209c42534cc&_noconfig=true",
        "method": "GET",
        "type": "Fetch",
        "referrerPolicy": "strict-origin-when-cross-origin",
        "referer": "https://www.kipling.com/",
        "status": 200,
        "size": 1075,
        "remoteIPAddress": "13.227.219.24",
        "responseHeaders": {
          "access-control-allow-origin": "https://www.kipling.com",
          "cache-control": "max-age=21600, s-max-age=21600",
          "etag": "W/\"04eb55737f5a8ab8a896b2ef9bd14475c\""
        },
        "responseBodyHash": "3b8890a82a3a78f6ad8b5fd024710263b91e8502ce774a62b050e5c914e70b35",
        "initiators": [
          "https://www.datadoghq-browser-agent.com/datadog-rum.js",
          "https://ui.powerreviews.com/tag-builds/10309/4.1/js/chunks/engine.js",
          "https://ui.powerreviews.com/tag-builds/10309/4.1/js/chunks/623.js"
        ],
        "time": 0.18009300000267103
      },
      {
        "url": "https://www.kipling.com/static/version1636522060/frontend/Vf/kipling/nl_NL/images/gallery.png",
        "method": "GET",
        "type": "Image",
        "referrerPolicy": "strict-origin-when-cross-origin",
        "referer": "https://www.kipling.com/static/version1636522060/_cache/merged/b2dea1ece461dcb9ca9ce0a800b92a00.min.css",
        "status": 200,
        "size": 10204,
        "remoteIPAddress": "23.222.38.47",
        "responseHeaders": {
          "cache-control": "max-age=31536000, public",
          "etag": "\"618b60b4-270e\"",
          "expires": "Sun, 27 Nov 2022 01:18:22 GMT"
        },
        "responseBodyHash": "9217d0af80b5513510dd0c35191c8ed14c6069e01bd42ebc6c25ad48b22b4bfc",
        "initiators": [
          "https://www.kipling.com/static/version1636522060/_cache/merged/b2dea1ece461dcb9ca9ce0a800b92a00.min.css"
        ],
        "time": 0.005499000020790845
      },
      {
        "url": "https://www.kipling.com/static/version1636522060/frontend/Vf/kipling/nl_NL/images/loader-1.gif",
        "method": "GET",
        "type": "Image",
        "referrerPolicy": "strict-origin-when-cross-origin",
        "referer": "https://www.kipling.com/static/version1636522060/_cache/merged/b2dea1ece461dcb9ca9ce0a800b92a00.min.css",
        "status": 200,
        "size": 17480,
        "remoteIPAddress": "23.222.38.47",
        "responseHeaders": {
          "cache-control": "max-age=31536000, public",
          "etag": "\"618b60b4-4367\"",
          "expires": "Sat, 26 Nov 2022 06:53:40 GMT"
        },
        "responseBodyHash": "06e4bafcda446712fbbbb8621cf55f42edd7c92d9f5964f33f828a7039d7279e",
        "initiators": [
          "https://www.kipling.com/static/version1636522060/_cache/merged/b2dea1ece461dcb9ca9ce0a800b92a00.min.css"
        ],
        "time": 0.009721999987959862
      },
      {
        "url": "https://www.kipling.com/media/catalog/product/cache/9d7c896cfb4307ce2143e4873e3c9dcb/K/I/KI4363X4600_999_5_1.jpg",
        "method": "GET",
        "type": "Image",
        "referrerPolicy": "strict-origin-when-cross-origin",
        "referer": "https://www.kipling.com/nl-nl/allie-black-mist-ki4363x4600-999.html",
        "status": 200,
        "size": 168463,
        "remoteIPAddress": "23.222.38.47",
        "responseHeaders": {
          "cache-control": "max-age=31536000, public",
          "etag": "\"60775b8b-28fdd\"",
          "expires": "Sun, 27 Nov 2022 09:35:48 GMT"
        },
        "responseBodyHash": "d318e7c07c779c11aa6a4a822f9d09172feed1e711e720fb879eb47932a13954",
        "initiators": [
          "https://www.kipling.com/static/version1636522060/frontend/Vf/kipling/nl_NL/magepack/bundle-product.min.js",
          "https://www.kipling.com/static/version1636522060/frontend/Vf/kipling/nl_NL/magepack/bundle-common.min.js",
          "https://www.kipling.com/static/version1636522060/_cache/merged/33c3a92e596bcb0a6527f8461165bcad.min.js"
        ],
        "time": 0.0381690000067465
      },
      {
        "url": "https://www.kipling.com/media/catalog/product/cache/9d7c896cfb4307ce2143e4873e3c9dcb/K/I/KI4363X4600_999_2_1.jpg",
        "method": "GET",
        "type": "Image",
        "referrerPolicy": "strict-origin-when-cross-origin",
        "referer": "https://www.kipling.com/nl-nl/allie-black-mist-ki4363x4600-999.html",
        "status": 200,
        "size": 90923,
        "remoteIPAddress": "23.222.38.47",
        "responseHeaders": {
          "cache-control": "max-age=31536000, public",
          "etag": "\"60774ae9-161a6\"",
          "expires": "Sun, 27 Nov 2022 13:29:36 GMT"
        },
        "responseBodyHash": "5e16d52eff201df45b01dd2cf8d62ce584c5c7f75ca40c517ccc815aa89a60f5",
        "initiators": [
          "https://www.kipling.com/static/version1636522060/frontend/Vf/kipling/nl_NL/magepack/bundle-product.min.js",
          "https://www.kipling.com/static/version1636522060/frontend/Vf/kipling/nl_NL/magepack/bundle-common.min.js",
          "https://www.kipling.com/static/version1636522060/_cache/merged/33c3a92e596bcb0a6527f8461165bcad.min.js"
        ],
        "time": 0.05211700001382269
      },
      {
        "url": "https://www.kipling.com/media/catalog/product/cache/69c42060bf1e6a2ec2ad9e4a7a55941c/K/I/KI4363X4600_999_1_1.jpg",
        "method": "GET",
        "type": "Image",
        "referrerPolicy": "strict-origin-when-cross-origin",
        "referer": "https://www.kipling.com/nl-nl/allie-black-mist-ki4363x4600-999.html",
        "status": 200,
        "size": 2243,
        "remoteIPAddress": "23.222.38.47",
        "responseHeaders": {
          "cache-control": "max-age=31536000, public",
          "etag": "\"60774550-806\"",
          "expires": "Sun, 27 Nov 2022 13:29:36 GMT"
        },
        "responseBodyHash": "eb5a6322eadb5110d892a752983db2854f3c6e2511a4e78a0ce2365f2d2317c1",
        "initiators": [
          "https://www.kipling.com/static/version1636522060/frontend/Vf/kipling/nl_NL/magepack/bundle-product.min.js",
          "https://www.kipling.com/static/version1636522060/frontend/Vf/kipling/nl_NL/magepack/bundle-common.min.js",
          "https://www.kipling.com/static/version1636522060/_cache/merged/33c3a92e596bcb0a6527f8461165bcad.min.js"
        ],
        "time": 0.03532000002451241
      },
      {
        "url": "https://www.kipling.com/media/catalog/product/cache/69c42060bf1e6a2ec2ad9e4a7a55941c/K/I/KI4363X4600_999_2_1.jpg",
        "method": "GET",
        "type": "Image",
        "referrerPolicy": "strict-origin-when-cross-origin",
        "referer": "https://www.kipling.com/nl-nl/allie-black-mist-ki4363x4600-999.html",
        "status": 200,
        "size": 1844,
        "remoteIPAddress": "23.222.38.47",
        "responseHeaders": {
          "cache-control": "max-age=31536000, public",
          "etag": "\"60774ae9-676\"",
          "expires": "Sun, 27 Nov 2022 08:38:38 GMT"
        },
        "responseBodyHash": "4db00b9ad308ab3c963ef9ece01b6ab7e79d0411879ece2145911b828c384321",
        "initiators": [
          "https://www.kipling.com/static/version1636522060/frontend/Vf/kipling/nl_NL/magepack/bundle-product.min.js",
          "https://www.kipling.com/static/version1636522060/frontend/Vf/kipling/nl_NL/magepack/bundle-common.min.js",
          "https://www.kipling.com/static/version1636522060/_cache/merged/33c3a92e596bcb0a6527f8461165bcad.min.js"
        ],
        "time": 0.051100000011501834
      },
      {
        "url": "https://www.kipling.com/media/catalog/product/cache/69c42060bf1e6a2ec2ad9e4a7a55941c/K/I/KI4363X4600_999_3_1.jpg",
        "method": "GET",
        "type": "Image",
        "referrerPolicy": "strict-origin-when-cross-origin",
        "referer": "https://www.kipling.com/nl-nl/allie-black-mist-ki4363x4600-999.html",
        "status": 200,
        "size": 2391,
        "remoteIPAddress": "23.222.38.47",
        "responseHeaders": {
          "cache-control": "max-age=31536000, public",
          "etag": "\"60775056-89a\"",
          "expires": "Sun, 27 Nov 2022 13:29:36 GMT"
        },
        "responseBodyHash": "04bf62e8afbd7d035152f92ca4522cba187d92a52dfdf1ac474f4baafa81ad6b",
        "initiators": [
          "https://www.kipling.com/static/version1636522060/frontend/Vf/kipling/nl_NL/magepack/bundle-product.min.js",
          "https://www.kipling.com/static/version1636522060/frontend/Vf/kipling/nl_NL/magepack/bundle-common.min.js",
          "https://www.kipling.com/static/version1636522060/_cache/merged/33c3a92e596bcb0a6527f8461165bcad.min.js"
        ],
        "time": 0.05924500001128763
      },
      {
        "url": "https://www.kipling.com/media/catalog/product/cache/69c42060bf1e6a2ec2ad9e4a7a55941c/K/I/KI4363X4600_999_4_1.jpg",
        "method": "GET",
        "type": "Image",
        "referrerPolicy": "strict-origin-when-cross-origin",
        "referer": "https://www.kipling.com/nl-nl/allie-black-mist-ki4363x4600-999.html",
        "status": 200,
        "size": 2542,
        "remoteIPAddress": "23.222.38.47",
        "responseHeaders": {
          "cache-control": "max-age=31536000, public",
          "etag": "\"607755c7-931\"",
          "expires": "Sun, 27 Nov 2022 08:35:00 GMT"
        },
        "responseBodyHash": "1ddf3007187dfa41ccd6212a379931561ad7b40d22ab5a94e8686b3fc05285d6",
        "initiators": [
          "https://www.kipling.com/static/version1636522060/frontend/Vf/kipling/nl_NL/magepack/bundle-product.min.js",
          "https://www.kipling.com/static/version1636522060/frontend/Vf/kipling/nl_NL/magepack/bundle-common.min.js",
          "https://www.kipling.com/static/version1636522060/_cache/merged/33c3a92e596bcb0a6527f8461165bcad.min.js"
        ],
        "time": 0.06171899999026209
      },
      {
        "url": "https://www.kipling.com/media/catalog/product/cache/69c42060bf1e6a2ec2ad9e4a7a55941c/K/I/KI4363X4600_999_5_1.jpg",
        "method": "GET",
        "type": "Image",
        "referrerPolicy": "strict-origin-when-cross-origin",
        "referer": "https://www.kipling.com/nl-nl/allie-black-mist-ki4363x4600-999.html",
        "status": 200,
        "size": 3037,
        "remoteIPAddress": "23.222.38.47",
        "responseHeaders": {
          "cache-control": "max-age=31536000, public",
          "etag": "\"60775b8b-b1f\"",
          "expires": "Sun, 27 Nov 2022 09:35:48 GMT"
        },
        "responseBodyHash": "5154346e61e99c4f21c725bf28771d20a81b0bafabec05bebb8a2984bed70f84",
        "initiators": [
          "https://www.kipling.com/static/version1636522060/frontend/Vf/kipling/nl_NL/magepack/bundle-product.min.js",
          "https://www.kipling.com/static/version1636522060/frontend/Vf/kipling/nl_NL/magepack/bundle-common.min.js",
          "https://www.kipling.com/static/version1636522060/_cache/merged/33c3a92e596bcb0a6527f8461165bcad.min.js"
        ],
        "time": 0.058625000005122274
      },
      {
        "url": "https://www.kipling.com/static/version1636522060/frontend/Vf/kipling/nl_NL/MSP_ReCaptcha/js/reCaptcha.min.js",
        "method": "GET",
        "type": "Script",
        "referrerPolicy": "strict-origin-when-cross-origin",
        "referer": "https://www.kipling.com/nl-nl/allie-black-mist-ki4363x4600-999.html",
        "status": 200,
        "size": 1135,
        "remoteIPAddress": "23.222.38.47",
        "responseHeaders": {
          "cache-control": "max-age=31536000, public",
          "etag": "W/\"618b60b4-b57\"",
          "expires": "Sun, 27 Nov 2022 01:18:50 GMT"
        },
        "responseBodyHash": "e28f569d6ac2cf6c4ef31c16cbcdd2bfe735157f6853203359174f6d683b833b",
        "initiators": [
          "https://www.kipling.com/static/version1636522060/_cache/merged/33c3a92e596bcb0a6527f8461165bcad.min.js",
          "https://www.kipling.com/static/version1636522060/frontend/Vf/kipling/nl_NL/magepack/bundle-common.min.js"
        ],
        "time": 0.014966999995522201
      },
      {
        "url": "https://www.kipling.com/static/version1636522060/frontend/Vf/kipling/nl_NL/Magento_Swatches/js/swatch-renderer-extend.min.js",
        "method": "GET",
        "type": "Script",
        "referrerPolicy": "strict-origin-when-cross-origin",
        "referer": "https://www.kipling.com/nl-nl/allie-black-mist-ki4363x4600-999.html",
        "status": 200,
        "size": 1059,
        "remoteIPAddress": "23.222.38.47",
        "responseHeaders": {
          "cache-control": "max-age=31536000, public",
          "etag": "W/\"618b60b6-b80\"",
          "expires": "Sun, 27 Nov 2022 01:26:25 GMT"
        },
        "responseBodyHash": "1bcb2d34a76a9089cfb4b01eca72ad6d52e0a626668c51e2653d60c2c9b0725f",
        "initiators": [
          "https://www.kipling.com/static/version1636522060/_cache/merged/33c3a92e596bcb0a6527f8461165bcad.min.js",
          "https://www.kipling.com/static/version1636522060/frontend/Vf/kipling/nl_NL/magepack/bundle-common.min.js"
        ],
        "time": 0.006877999985590577
      },
      {
        "url": "https://www.kipling.com/media/catalog/product/cache/29ced269b80dec0b4b12d4d575e52204/K/I/KI4363X4600_999_1_1.jpg",
        "method": "GET",
        "type": "Image",
        "referrerPolicy": "strict-origin-when-cross-origin",
        "referer": "https://www.kipling.com/nl-nl/allie-black-mist-ki4363x4600-999.html",
        "status": 200,
        "size": 241316,
        "remoteIPAddress": "23.222.38.47",
        "responseHeaders": {
          "cache-control": "max-age=31536000, public",
          "etag": "\"6077454f-3abd1\"",
          "expires": "Sun, 27 Nov 2022 13:29:49 GMT"
        },
        "responseBodyHash": "4d08d2cd712b87225bb1cb32e47985764b3b8e7dd81f693a790ad5e9a23c19ba",
        "initiators": [
          "https://www.kipling.com/static/version1636522060/frontend/Vf/kipling/nl_NL/magepack/bundle-product.min.js",
          "https://www.kipling.com/static/version1636522060/frontend/Vf/kipling/nl_NL/magepack/bundle-common.min.js",
          "https://www.kipling.com/static/version1636522060/_cache/merged/33c3a92e596bcb0a6527f8461165bcad.min.js"
        ],
        "time": 0.012645999988308176
      },
      {
        "url": "https://ui.powerreviews.com/tag-builds/10309/4.1/js/chunks/712.js",
        "method": "GET",
        "type": "Script",
        "referrerPolicy": "strict-origin-when-cross-origin",
        "referer": "https://www.kipling.com/",
        "status": 200,
        "size": 5348,
        "remoteIPAddress": "65.9.83.58",
        "responseHeaders": {
          "access-control-allow-origin": "*",
          "cache-control": "max-age=604800000",
          "etag": "W/\"46cf1967c19549c2bf2aba0443b00713\""
        },
        "responseBodyHash": "666023b415939711a80c3e1c4edfc7967cb819f511b0e36cb4d4956d29243d71",
        "initiators": [
          "https://ui.powerreviews.com/stable/4.1/ui.js",
          "https://ui.powerreviews.com/tag-builds/10309/4.1/js/chunks/engine.js",
          "https://ui.powerreviews.com/tag-builds/10309/4.1/js/chunks/623.js"
        ],
        "time": 0.008138999983202666
      },
      {
        "url": "https://ui.powerreviews.com/tag-builds/10309/4.1/js/chunks/152.js",
        "method": "GET",
        "type": "Script",
        "referrerPolicy": "strict-origin-when-cross-origin",
        "referer": "https://www.kipling.com/",
        "status": 200,
        "size": 3937,
        "remoteIPAddress": "65.9.83.58",
        "responseHeaders": {
          "access-control-allow-origin": "*",
          "cache-control": "max-age=604800000",
          "etag": "W/\"b8b56bfb72a1ccf9aefb63d46509140c\""
        },
        "responseBodyHash": "ada8fcf1a22634fc88425518ed558336bb56e947d1071699657faf41ddb43146",
        "initiators": [
          "https://ui.powerreviews.com/stable/4.1/ui.js",
          "https://ui.powerreviews.com/tag-builds/10309/4.1/js/chunks/engine.js",
          "https://ui.powerreviews.com/tag-builds/10309/4.1/js/chunks/623.js"
        ],
        "time": 0.007326999999349937
      },
      {
        "url": "https://ui.powerreviews.com/tag-builds/10309/4.1/js/chunks/858.js",
        "method": "GET",
        "type": "Script",
        "referrerPolicy": "strict-origin-when-cross-origin",
        "referer": "https://www.kipling.com/",
        "status": 200,
        "size": 6899,
        "remoteIPAddress": "65.9.83.58",
        "responseHeaders": {
          "access-control-allow-origin": "*",
          "cache-control": "max-age=604800000",
          "etag": "W/\"cb923701bbd46fc8b0359eb4436ed644\""
        },
        "responseBodyHash": "d42d329392aa80c3d2044893c699852577b769669437c27adb107880a5dd4b30",
        "initiators": [
          "https://ui.powerreviews.com/stable/4.1/ui.js",
          "https://ui.powerreviews.com/tag-builds/10309/4.1/js/chunks/engine.js",
          "https://ui.powerreviews.com/tag-builds/10309/4.1/js/chunks/623.js"
        ],
        "time": 0.003448999981628731
      },
      {
        "url": "https://ui.powerreviews.com/tag-builds/10309/4.1/js/chunks/293.js",
        "method": "GET",
        "type": "Script",
        "referrerPolicy": "strict-origin-when-cross-origin",
        "referer": "https://www.kipling.com/",
        "status": 200,
        "size": 20435,
        "remoteIPAddress": "65.9.83.58",
        "responseHeaders": {
          "access-control-allow-origin": "*",
          "cache-control": "max-age=604800000",
          "etag": "W/\"b8e2e6aedd973886cffe5d33e36f62ce\""
        },
        "responseBodyHash": "34d4a70723342aa4a167324351c3ae9fdafe595037a28724774b0a39ee3b07e1",
        "initiators": [
          "https://ui.powerreviews.com/stable/4.1/ui.js",
          "https://ui.powerreviews.com/tag-builds/10309/4.1/js/chunks/engine.js",
          "https://ui.powerreviews.com/tag-builds/10309/4.1/js/chunks/623.js"
        ],
        "time": 0.00777100000414066
      },
      {
        "url": "https://ui.powerreviews.com/tag-builds/10309/4.1/js/chunks/war.js",
        "method": "GET",
        "type": "Script",
        "referrerPolicy": "strict-origin-when-cross-origin",
        "referer": "https://www.kipling.com/",
        "status": 200,
        "size": 15452,
        "remoteIPAddress": "65.9.83.58",
        "responseHeaders": {
          "access-control-allow-origin": "*",
          "cache-control": "max-age=604800000",
          "etag": "W/\"04ea8ac82e2492b4da85a172589593af\""
        },
        "responseBodyHash": "7a65846aa8d63417769129b621fd3b3d7e17a4dc76b300f0923c765bf9ac2c92",
        "initiators": [
          "https://ui.powerreviews.com/stable/4.1/ui.js",
          "https://ui.powerreviews.com/tag-builds/10309/4.1/js/chunks/engine.js",
          "https://ui.powerreviews.com/tag-builds/10309/4.1/js/chunks/623.js"
        ],
        "time": 0.010661999986041337
      },
      {
        "url": "https://ui.powerreviews.com/tag-builds/10309/4.1/js/chunks/695.js",
        "method": "GET",
        "type": "Script",
        "referrerPolicy": "strict-origin-when-cross-origin",
        "referer": "https://www.kipling.com/",
        "status": 200,
        "size": 2213,
        "remoteIPAddress": "65.9.83.58",
        "responseHeaders": {
          "access-control-allow-origin": "*",
          "cache-control": "max-age=604800000",
          "etag": "W/\"32cb5697450262a16b9d8459acf54328\""
        },
        "responseBodyHash": "54e81ae3ac1a9ca47fef1f29be6f01e80f9ce8d678d27eb39611dff0cda98433",
        "initiators": [
          "https://ui.powerreviews.com/stable/4.1/ui.js",
          "https://ui.powerreviews.com/tag-builds/10309/4.1/js/chunks/engine.js",
          "https://ui.powerreviews.com/tag-builds/10309/4.1/js/chunks/623.js"
        ],
        "time": 0.007293999980902299
      },
      {
        "url": "https://ui.powerreviews.com/tag-builds/10309/4.1/js/chunks/432.js",
        "method": "GET",
        "type": "Script",
        "referrerPolicy": "strict-origin-when-cross-origin",
        "referer": "https://www.kipling.com/",
        "status": 200,
        "size": 4074,
        "remoteIPAddress": "65.9.83.58",
        "responseHeaders": {
          "access-control-allow-origin": "*",
          "cache-control": "max-age=604800000",
          "etag": "W/\"5386195c6dd285e32198690a819effc9\""
        },
        "responseBodyHash": "3f08211b4ad443494fa3beb06bd43d985f9a405da5d211a3d92653f7aec1ac66",
        "initiators": [
          "https://ui.powerreviews.com/stable/4.1/ui.js",
          "https://ui.powerreviews.com/tag-builds/10309/4.1/js/chunks/engine.js",
          "https://ui.powerreviews.com/tag-builds/10309/4.1/js/chunks/623.js"
        ],
        "time": 0.008159999997587875
      },
      {
        "url": "https://ui.powerreviews.com/tag-builds/10309/4.1/js/chunks/review-snippet.js",
        "method": "GET",
        "type": "Script",
        "referrerPolicy": "strict-origin-when-cross-origin",
        "referer": "https://www.kipling.com/",
        "status": 200,
        "size": 4069,
        "remoteIPAddress": "65.9.83.58",
        "responseHeaders": {
          "access-control-allow-origin": "*",
          "cache-control": "max-age=604800000",
          "etag": "W/\"d8e1e220a409faca42c9452242e950f1\""
        },
        "responseBodyHash": "a4e7756d2f7aed60e274cf4d752afb05cc92b8ae46530f746f030a39e4e7cc7e",
        "initiators": [
          "https://ui.powerreviews.com/stable/4.1/ui.js",
          "https://ui.powerreviews.com/tag-builds/10309/4.1/js/chunks/engine.js",
          "https://ui.powerreviews.com/tag-builds/10309/4.1/js/chunks/623.js"
        ],
        "time": 0.0071650000172667205
      },
      {
        "url": "https://ui.powerreviews.com/tag-builds/10309/4.1/js/chunks/559.js",
        "method": "GET",
        "type": "Script",
        "referrerPolicy": "strict-origin-when-cross-origin",
        "referer": "https://www.kipling.com/",
        "status": 200,
        "size": 7791,
        "remoteIPAddress": "65.9.83.58",
        "responseHeaders": {
          "access-control-allow-origin": "*",
          "cache-control": "max-age=604800000",
          "etag": "W/\"e880603b1a7d88b94254bc8a477b8505\""
        },
        "responseBodyHash": "6033ab24ac6ba212a4700ea8aa1b67fd05fd09729ed0e4b5ef9c5bba8b6aa57f",
        "initiators": [
          "https://ui.powerreviews.com/stable/4.1/ui.js",
          "https://ui.powerreviews.com/tag-builds/10309/4.1/js/chunks/engine.js",
          "https://ui.powerreviews.com/tag-builds/10309/4.1/js/chunks/623.js"
        ],
        "time": 0.008827000012388453
      },
      {
        "url": "https://ui.powerreviews.com/tag-builds/10309/4.1/js/chunks/qa-snippet.js",
        "method": "GET",
        "type": "Script",
        "referrerPolicy": "strict-origin-when-cross-origin",
        "referer": "https://www.kipling.com/",
        "status": 200,
        "size": 4714,
        "remoteIPAddress": "65.9.83.58",
        "responseHeaders": {
          "access-control-allow-origin": "*",
          "cache-control": "max-age=604800000",
          "etag": "W/\"01661b2ac61a30994d26a1947f0fe511\""
        },
        "responseBodyHash": "1299d3308df2449936cb815758db52cdd007895c3ef3ea5f8e3a56aa376c9c80",
        "initiators": [
          "https://ui.powerreviews.com/stable/4.1/ui.js",
          "https://ui.powerreviews.com/tag-builds/10309/4.1/js/chunks/engine.js",
          "https://ui.powerreviews.com/tag-builds/10309/4.1/js/chunks/623.js"
        ],
        "time": 0.007358000002568588
      },
      {
        "url": "https://ui.powerreviews.com/tag-builds/10309/4.1/js/chunks/932.js",
        "method": "GET",
        "type": "Script",
        "referrerPolicy": "strict-origin-when-cross-origin",
        "referer": "https://www.kipling.com/",
        "status": 200,
        "size": 31028,
        "remoteIPAddress": "65.9.83.58",
        "responseHeaders": {
          "access-control-allow-origin": "*",
          "cache-control": "max-age=604800000",
          "etag": "W/\"19dc4ebee65a640e2240158932ee5028\""
        },
        "responseBodyHash": "78c977938b43e33f48c1088f3841fdb521a6df77e2c29a25e6679ae58f2d8248",
        "initiators": [
          "https://ui.powerreviews.com/stable/4.1/ui.js",
          "https://ui.powerreviews.com/tag-builds/10309/4.1/js/chunks/engine.js",
          "https://ui.powerreviews.com/tag-builds/10309/4.1/js/chunks/623.js"
        ],
        "time": 0.007061000011162832
      },
      {
        "url": "https://ui.powerreviews.com/tag-builds/10309/4.1/js/chunks/519.js",
        "method": "GET",
        "type": "Script",
        "referrerPolicy": "strict-origin-when-cross-origin",
        "referer": "https://www.kipling.com/",
        "status": 200,
        "size": 5964,
        "remoteIPAddress": "65.9.83.58",
        "responseHeaders": {
          "access-control-allow-origin": "*",
          "cache-control": "max-age=604800000",
          "etag": "W/\"7745e85983aac5af999791e0718c5176\""
        },
        "responseBodyHash": "538989871265d41e52a4ebd4f1b03e2003c2a5d21691c484a87130bd7b6b3f86",
        "initiators": [
          "https://ui.powerreviews.com/stable/4.1/ui.js",
          "https://ui.powerreviews.com/tag-builds/10309/4.1/js/chunks/engine.js",
          "https://ui.powerreviews.com/tag-builds/10309/4.1/js/chunks/623.js"
        ],
        "time": 0.00716499998816289
      },
      {
        "url": "https://ui.powerreviews.com/tag-builds/10309/4.1/js/chunks/934.js",
        "method": "GET",
        "type": "Script",
        "referrerPolicy": "strict-origin-when-cross-origin",
        "referer": "https://www.kipling.com/",
        "status": 200,
        "size": 15587,
        "remoteIPAddress": "65.9.83.58",
        "responseHeaders": {
          "access-control-allow-origin": "*",
          "cache-control": "max-age=604800000",
          "etag": "W/\"b85d4a39f218b52f2a2a4c7d82b027de\""
        },
        "responseBodyHash": "f5324cca2e9b619f750a321834b8d511a5654027d3dbbe29cf631c2b611ede6e",
        "initiators": [
          "https://ui.powerreviews.com/stable/4.1/ui.js",
          "https://ui.powerreviews.com/tag-builds/10309/4.1/js/chunks/engine.js",
          "https://ui.powerreviews.com/tag-builds/10309/4.1/js/chunks/623.js"
        ],
        "time": 0.006691999995382503
      },
      {
        "url": "https://ui.powerreviews.com/tag-builds/10309/4.1/js/chunks/830.js",
        "method": "GET",
        "type": "Script",
        "referrerPolicy": "strict-origin-when-cross-origin",
        "referer": "https://www.kipling.com/",
        "status": 200,
        "size": 10319,
        "remoteIPAddress": "65.9.83.58",
        "responseHeaders": {
          "access-control-allow-origin": "*",
          "cache-control": "max-age=604800000",
          "etag": "W/\"62e9c47beaf7d9996026edad76f7f0ce\""
        },
        "responseBodyHash": "c0e2a30fb957221c9ab4de14aaebaf6581bbf1e5f9938deea88504b84332aaa4",
        "initiators": [
          "https://ui.powerreviews.com/stable/4.1/ui.js",
          "https://ui.powerreviews.com/tag-builds/10309/4.1/js/chunks/engine.js",
          "https://ui.powerreviews.com/tag-builds/10309/4.1/js/chunks/623.js"
        ],
        "time": 0.005440999986603856
      },
      {
        "url": "https://ui.powerreviews.com/tag-builds/10309/4.1/js/chunks/review-display.js",
        "method": "GET",
        "type": "Script",
        "referrerPolicy": "strict-origin-when-cross-origin",
        "referer": "https://www.kipling.com/",
        "status": 200,
        "size": 3339,
        "remoteIPAddress": "65.9.83.58",
        "responseHeaders": {
          "access-control-allow-origin": "*",
          "cache-control": "max-age=604800000",
          "etag": "W/\"34c5cf37afb378d3d105bf5fccca81ae\""
        },
        "responseBodyHash": "9eb5c49d1a691e64b84f62612fd6a2b6c1e7588d64eb15353199dcdb8035752c",
        "initiators": [
          "https://ui.powerreviews.com/stable/4.1/ui.js",
          "https://ui.powerreviews.com/tag-builds/10309/4.1/js/chunks/engine.js",
          "https://ui.powerreviews.com/tag-builds/10309/4.1/js/chunks/623.js"
        ],
        "time": 0.008698999998159707
      },
      {
        "url": "https://ui.powerreviews.com/tag-builds/10309/4.1/js/chunks/category-snippet.js",
        "method": "GET",
        "type": "Script",
        "referrerPolicy": "strict-origin-when-cross-origin",
        "referer": "https://www.kipling.com/",
        "status": 200,
        "size": 2903,
        "remoteIPAddress": "65.9.83.58",
        "responseHeaders": {
          "access-control-allow-origin": "*",
          "cache-control": "max-age=604800000",
          "etag": "W/\"16572a7ee78c3e083e7f491c41393b09\""
        },
        "responseBodyHash": "edbac57a65682a42dfd80def8732ce8637e3bc6a05abf337f7c29349f55d0684",
        "initiators": [
          "https://ui.powerreviews.com/stable/4.1/ui.js",
          "https://ui.powerreviews.com/tag-builds/10309/4.1/js/chunks/engine.js",
          "https://ui.powerreviews.com/tag-builds/10309/4.1/js/chunks/623.js"
        ],
        "time": 0.006434000009903684
      },
      {
        "url": "https://t.powerreviews.com/t/v1.gif?e=fp&id=uej716RICr&uid=HT-MONN0oa&t=kxgtwg2l&l=nl_NL&mgid=49021&mid=811778&pid=ALLIE&p=https%3A%2F%2Fwww.kipling.com%2Fnl-nl%2Fallie-black-mist-ki4363x4600-999.html&v=4.1&vv=10309&n=ALLIE&d=Het%20Allie%20medium%20etui%20is%20veelzijdig%20genoeg%20voor%20pennen%2C%20schrijfgerei%20of%20kleine%20items%20in%20te%20stoppen%20en%20is%20perfect%20voor%20dagelijks%20gebruik.%20Organiseer%20alles%20in%20twee%20handige%20vakken%20met%20rits%20en%20stop%20je%20etui%20in%20je%20favoriete%20Kipling-rugzak%20of%20draagtas.%20Robot-aapje%20Rond%20Kipling-logo%202%20hoofdvakken%20met%20ritssl&pu=https%3A%2F%2Fwww.kipling.com%2Fnl-nl%2Fschooltas-c10612%2Fallie-black-mist-ki4363x4600-999.html&iu=https%3A%2F%2Fwww.kipling.com%2Fmedia%2Fcatalog%2Fproduct%2Fcache%2F29ced269b80dec0b4b12d4d575e52204%2FK%2FI%2FKI4363X4600_999_1_1.jpg&pri=45.000000&cn=Sale&is=1",
        "method": "GET",
        "type": "Image",
        "referrerPolicy": "strict-origin-when-cross-origin",
        "referer": "https://www.kipling.com/",
        "status": 200,
        "size": 492,
        "remoteIPAddress": "13.227.219.49",
        "responseHeaders": {
          "etag": "\"fc94fb0c3ed8a8f909dbc7630a0987ff\""
        },
        "responseBodyHash": "10f9bfa42bb96c99729c9b2fee669803ad9c6fcd434d8d7d60a8dc8f5f7cc331",
        "initiators": [
          "https://ui.powerreviews.com/tag-builds/10309/4.1/js/chunks/engine.js",
          "https://ui.powerreviews.com/tag-builds/10309/4.1/js/chunks/623.js"
        ],
        "time": 0.2849090000090655
      },
      {
        "url": "https://t.powerreviews.com/t/v1.gif?e=fp&id=0Quo0hg8cR&uid=HT-MONN0oa&t=kxgtwg2m&l=nl_NL&mgid=49021&mid=811778&pid=ALLIE&pidv=ALLIE_KPKI4363O76OS1&p=https%3A%2F%2Fwww.kipling.com%2Fnl-nl%2Fallie-black-mist-ki4363x4600-999.html&v=4.1&vv=10309&n=ALLIE&pu=https%3A%2F%2Fwww.kipling.com%2Fnl-nl%2Fschooltas-c10612%2Fallie-monster-pink-m-ki4363o7600-999.html&iu=https%3A%2F%2Fwww.kipling.com%2Fmedia%2Fcatalog%2Fproduct%2Fcache%2F29ced269b80dec0b4b12d4d575e52204%2FK%2FI%2FKI4363X4600_999_1_1.jpg&pri=45.000000&cn=Sale&is=1",
        "method": "GET",
        "type": "Image",
        "referrerPolicy": "strict-origin-when-cross-origin",
        "referer": "https://www.kipling.com/",
        "status": 200,
        "size": 499,
        "remoteIPAddress": "13.227.219.49",
        "responseHeaders": {
          "etag": "\"fc94fb0c3ed8a8f909dbc7630a0987ff\""
        },
        "responseBodyHash": "10f9bfa42bb96c99729c9b2fee669803ad9c6fcd434d8d7d60a8dc8f5f7cc331",
        "initiators": [
          "https://ui.powerreviews.com/tag-builds/10309/4.1/js/chunks/engine.js",
          "https://ui.powerreviews.com/tag-builds/10309/4.1/js/chunks/623.js"
        ],
        "time": 0.6263810000091325
      },
      {
        "url": "https://t.powerreviews.com/t/v1.gif?e=fp&id=rIW4hTBlY7&uid=HT-MONN0oa&t=kxgtwg2m&l=nl_NL&mgid=49021&mid=811778&pid=ALLIE&pidv=ALLIE_KPKI4363X46OS1&p=https%3A%2F%2Fwww.kipling.com%2Fnl-nl%2Fallie-black-mist-ki4363x4600-999.html&v=4.1&vv=10309&n=ALLIE&pu=https%3A%2F%2Fwww.kipling.com%2Fnl-nl%2Fschooltas-c10612%2Fallie-black-mist-ki4363x4600-999.html&iu=https%3A%2F%2Fwww.kipling.com%2Fmedia%2Fcatalog%2Fproduct%2Fcache%2F29ced269b80dec0b4b12d4d575e52204%2FK%2FI%2FKI4363X4600_999_1_1.jpg&pri=45.000000&cn=Sale&is=1",
        "method": "GET",
        "type": "Image",
        "referrerPolicy": "strict-origin-when-cross-origin",
        "referer": "https://www.kipling.com/",
        "status": 200,
        "size": 492,
        "remoteIPAddress": "13.227.219.49",
        "responseHeaders": {
          "etag": "\"fc94fb0c3ed8a8f909dbc7630a0987ff\""
        },
        "responseBodyHash": "10f9bfa42bb96c99729c9b2fee669803ad9c6fcd434d8d7d60a8dc8f5f7cc331",
        "initiators": [
          "https://ui.powerreviews.com/tag-builds/10309/4.1/js/chunks/engine.js",
          "https://ui.powerreviews.com/tag-builds/10309/4.1/js/chunks/623.js"
        ],
        "time": 0.6256249999860302
      },
      {
        "url": "https://www.google.com/recaptcha/api.js?onload=globalOnRecaptchaOnLoadCallback&render=explicit",
        "method": "GET",
        "type": "Script",
        "referrerPolicy": "strict-origin-when-cross-origin",
        "referer": "https://www.kipling.com/",
        "status": 200,
        "size": 1004,
        "remoteIPAddress": "142.251.36.36",
        "responseHeaders": {
          "cache-control": "private, max-age=300",
          "expires": "Wed, 22 Dec 2021 00:59:40 GMT"
        },
        "responseBodyHash": "2231caa846cc865f524b8ab1806e8ef47d8ced8af680cc6f2025ea1066787b99",
        "initiators": [
          "https://www.kipling.com/static/version1636522060/frontend/Vf/kipling/nl_NL/MSP_ReCaptcha/js/reCaptcha.min.js",
          "https://www.kipling.com/static/version1636522060/frontend/Vf/kipling/nl_NL/magepack/bundle-common.min.js",
          "https://www.kipling.com/static/version1636522060/_cache/merged/33c3a92e596bcb0a6527f8461165bcad.min.js"
        ],
        "time": 0.021800999995321035
      },
      {
        "url": "https://cdn.cookielaw.org/scripttemplates/otSDKStub.js",
        "method": "GET",
        "type": "Script",
        "referrerPolicy": "strict-origin-when-cross-origin",
        "referer": "https://www.kipling.com/",
        "status": 200,
        "size": 7127,
        "remoteIPAddress": "104.16.148.64",
        "responseHeaders": {
          "access-control-allow-origin": "*",
          "cache-control": "max-age=14400",
          "etag": "0x8D9C17FDD6FB88D"
        },
        "responseBodyHash": "4d2a74d8b25e1ccd4b1294b0b937804bc24aeea7f46edad3f3c1f91604d2708c",
        "initiators": [
          "https://www.googletagmanager.com/gtm.js?id=GTM-NCCHW6"
        ],
        "time": 0.024006999999983236
      },
      {
        "url": "https://rum-static.pingdom.net/prum.min.js",
        "method": "GET",
        "type": "Script",
        "referrerPolicy": "strict-origin-when-cross-origin",
        "referer": "https://www.kipling.com/",
        "status": 200,
        "size": 2986,
        "remoteIPAddress": "104.22.54.104",
        "responseHeaders": {
          "access-control-allow-origin": "*",
          "cache-control": "max-age=43200",
          "etag": "W/\"609a8e42-1849\""
        },
        "responseBodyHash": "c19455754ead9313cc2221c64f1c66e8378501d8099bdcb3d90bb0b1a170b5ec",
        "initiators": [
          "https://www.googletagmanager.com/gtm.js?id=GTM-NCCHW6"
        ],
        "time": 0.036514999985229224
      },
      {
        "url": "https://www.kipling.com/static/version1636522060/frontend/Vf/kipling/nl_NL/Magento_Swatches/js/swatch-renderer.min.js",
        "method": "GET",
        "type": "Script",
        "referrerPolicy": "strict-origin-when-cross-origin",
        "referer": "https://www.kipling.com/nl-nl/allie-black-mist-ki4363x4600-999.html",
        "status": 200,
        "size": 6023,
        "remoteIPAddress": "23.222.38.47",
        "responseHeaders": {
          "cache-control": "max-age=31536000, public",
          "etag": "W/\"618b60b6-61fa\"",
          "expires": "Thu, 15 Dec 2022 09:14:09 GMT"
        },
        "responseBodyHash": "2e17e4e02c5b1352796a2c711d74600976e0e419db0d1f64abf60f657ef604f8",
        "initiators": [
          "https://www.kipling.com/static/version1636522060/_cache/merged/33c3a92e596bcb0a6527f8461165bcad.min.js",
          "https://www.kipling.com/static/version1636522060/frontend/Vf/kipling/nl_NL/magepack/bundle-common.min.js"
        ],
        "time": 0.011976999987382442
      },
      {
        "url": "https://www.kipling.com/static/version1636522060/frontend/Vf/kipling/nl_NL/Magento_Swatches/js/swatch-renderer-mixin.min.js",
        "method": "GET",
        "type": "Script",
        "referrerPolicy": "strict-origin-when-cross-origin",
        "referer": "https://www.kipling.com/nl-nl/allie-black-mist-ki4363x4600-999.html",
        "status": 200,
        "size": 1583,
        "remoteIPAddress": "23.222.38.47",
        "responseHeaders": {
          "cache-control": "max-age=31536000, public",
          "etag": "W/\"618b60b6-15ac\"",
          "expires": "Tue, 20 Dec 2022 13:00:17 GMT"
        },
        "responseBodyHash": "998a4f923e2ed4570e4325c6826970f026fbe6690f4f196eaf54eb63980f449a",
        "initiators": [
          "https://www.kipling.com/static/version1636522060/_cache/merged/33c3a92e596bcb0a6527f8461165bcad.min.js",
          "https://www.kipling.com/static/version1636522060/frontend/Vf/kipling/nl_NL/magepack/bundle-common.min.js"
        ],
        "time": 0.010322999994968995
      },
      {
        "url": "https://www.kipling.com/static/version1636522060/frontend/Vf/kipling/nl_NL/MSP_ReCaptcha/template/reCaptcha.html",
        "method": "GET",
        "type": "XHR",
        "referrerPolicy": "strict-origin-when-cross-origin",
        "referer": "https://www.kipling.com/nl-nl/allie-black-mist-ki4363x4600-999.html",
        "status": 200,
        "size": 1468,
        "remoteIPAddress": "23.222.38.47",
        "responseHeaders": {
          "cache-control": "max-age=315360000",
          "etag": "W/\"618b60b4-519\"",
          "expires": "Thu, 31 Dec 2037 23:55:55 GMT",
          "set-cookie": "bm_mi=89A2204FB4D9A80AACDDC92699EFCE6C~CPbPeOc51kgOL1UGvK6iROu8RDlmFl4IbiRGGL/Z61eJcMHRDCwoEqG6jT+bL30Dt8DPxOS6Xr5q09ZAzca2Zbue9JB0SLhuDTtcTvLUvI+67MksbIn/2iWVJCZjtgfA7RCrk3LSjF1TjjNO2k2roP1JM2z0sxxD6ryvKoUSIw2r258FniJvXUJM1sf+A61GEHQ9v8xeREMfkJY6QK/ZDDn9uAA2/i43PPH5ijltQJP6e+YQfmHWnWagKhrtkIhaahL+r0tFXQEXe1jqldqrXDOSJZCDAG0vq1yU43Sscv9o2Ojjr3IGbulBg+mfjnWfiJZwLA6XaSpAociCUdFq4TjuwY3hYgAcPCZesPd18hQ=; Domain=.kipling.com; Path=/; Max-Age=7199; HttpOnly\nbm_sv=A81479433BFCE2FAE612C725B75C6B4A~3HQT86+fNWxWSss7R7XLplSk0zjqcNKaBRau08xyRtQEftwQv9hpZOd9lmGayqDL8VT2P/+jGsmtyUiNTj5m2bPPQ1JfV3gi7n+/rzCsJfaKqgGwbzHjHq2Btr8PT04LKedTA4owOvPKkrieKF+VkAbrikPneFujVyigG26wtTA=; Domain=.kipling.com; Path=/; Max-Age=7200; HttpOnly"
        },
        "responseBodyHash": "0453f7992607a0517d9a82b9482029010948791d5fc70dfb24851dd85edce9d7",
        "initiators": [
          "https://www.datadoghq-browser-agent.com/datadog-rum.js",
          "https://www.kipling.com/static/version1636522060/frontend/Vf/kipling/nl_NL/magepack/bundle-common.min.js",
          "https://www.kipling.com/static/version1636522060/_cache/merged/33c3a92e596bcb0a6527f8461165bcad.min.js"
        ],
        "time": 0.03358399998978712
      },
      {
        "url": "https://www.gstatic.com/recaptcha/releases/VZKEDW9wslPbEc9RmzMqaOAP/recaptcha__en.js",
        "method": "GET",
        "type": "Script",
        "referrerPolicy": "strict-origin-when-cross-origin",
        "referer": "https://www.kipling.com/",
        "status": 200,
        "size": 138246,
        "remoteIPAddress": "142.251.36.35",
        "responseHeaders": {
          "access-control-allow-origin": "*",
          "cache-control": "public, max-age=31536000",
          "expires": "Wed, 21 Dec 2022 17:27:56 GMT"
        },
        "responseBodyHash": "de40f8e9a13821460fad3250442ee45458a1073661d67758f325b3a354995dd3",
        "initiators": [
          "https://www.google.com/recaptcha/api.js?onload=globalOnRecaptchaOnLoadCallback&render=explicit"
        ],
        "time": 0.01611399999819696
      },
      {
        "url": "https://cdn.cookielaw.org/consent/f808bc0e-5a8f-451f-91ed-3101cec5e8e3/f808bc0e-5a8f-451f-91ed-3101cec5e8e3.json",
        "method": "GET",
        "type": "XHR",
        "referrerPolicy": "strict-origin-when-cross-origin",
        "referer": "https://www.kipling.com/",
        "status": 200,
        "size": 1938,
        "remoteIPAddress": "104.16.148.64",
        "responseHeaders": {
          "access-control-allow-origin": "*",
          "cache-control": "public, max-age=14400",
          "etag": "0x8D9BEF6923BF168",
          "expires": "Wed, 22 Dec 2021 04:59:40 GMT"
        },
        "responseBodyHash": "f87f9a9e1c4f0d6d5887a055fb95b313dca76cea006d7a72eb5b67517f4790d1",
        "initiators": [
          "https://www.datadoghq-browser-agent.com/datadog-rum.js",
          "https://cdn.cookielaw.org/scripttemplates/otSDKStub.js"
        ],
        "time": 0.022234000003663823
      },
      {
        "url": "https://display.powerreviews.com/m/811778/l/nl_NL/product/ALLIE/reviews?apikey=b2d323a8-6479-4904-99cc-4209c42534cc&_noconfig=true",
        "method": "GET",
        "type": "Fetch",
        "referrerPolicy": "strict-origin-when-cross-origin",
        "referer": "https://www.kipling.com/",
        "status": 200,
        "size": 600,
        "remoteIPAddress": "13.227.219.24",
        "responseHeaders": {
          "access-control-allow-origin": "https://www.kipling.com",
          "cache-control": "max-age=21600, s-max-age=21600",
          "etag": "\"03d5b422d8153c19a8bdb001e7204cd47\""
        },
        "responseBodyHash": "c969a7060025d42d505eed64050a219e5607edae5151a05cf448d5c2630be313",
        "initiators": [
          "https://www.datadoghq-browser-agent.com/datadog-rum.js",
          "https://ui.powerreviews.com/tag-builds/10309/4.1/js/chunks/engine.js",
          "https://ui.powerreviews.com/tag-builds/10309/4.1/js/chunks/623.js",
          "https://ui.powerreviews.com/tag-builds/10309/4.1/js/chunks/review-snippet.js"
        ],
        "time": 0.012270999985048547
      },
      {
        "url": "https://display.powerreviews.com/m/811778/l/nl_NL/product/ALLIE/questions?_noconfig=true&apikey=b2d323a8-6479-4904-99cc-4209c42534cc",
        "method": "GET",
        "type": "XHR",
        "referrerPolicy": "strict-origin-when-cross-origin",
        "referer": "https://www.kipling.com/",
        "status": 200,
        "size": 567,
        "remoteIPAddress": "13.227.219.24",
        "responseHeaders": {
          "access-control-allow-origin": "https://www.kipling.com",
          "cache-control": "max-age=21600, s-max-age=21600",
          "etag": "\"01bd18f2b80e78d096c440a94a5285db7\""
        },
        "responseBodyHash": "768c211101d6af44b854104cbe2144b5d1137114c15c015b4ab76ef3cc9376d4",
        "initiators": [
          "https://www.datadoghq-browser-agent.com/datadog-rum.js",
          "https://ui.powerreviews.com/tag-builds/10309/4.1/js/chunks/623.js",
          "https://ui.powerreviews.com/tag-builds/10309/4.1/js/chunks/engine.js",
          "https://ui.powerreviews.com/tag-builds/10309/4.1/js/chunks/qa-snippet.js"
        ],
        "time": 0.00607900001341477
      },
      {
        "url": "https://display.powerreviews.com/m/811778/l/nl_NL/product/INIKO%2CELSIL%2CMIHO_M%2CMY_TOTE_BAG%2CELSIL%2CAMIEL/snippet?apikey=b2d323a8-6479-4904-99cc-4209c42534cc&_noconfig=true",
        "method": "GET",
        "type": "Fetch",
        "referrerPolicy": "strict-origin-when-cross-origin",
        "referer": "https://www.kipling.com/",
        "status": 200,
        "size": 844,
        "remoteIPAddress": "13.227.219.24",
        "responseHeaders": {
          "access-control-allow-origin": "https://www.kipling.com",
          "cache-control": "max-age=21600, s-max-age=21600",
          "etag": "\"03e2e8605622f66083325f2dd72b45808\""
        },
        "responseBodyHash": "fb360c3410a4573b3ecf44576302da617b6f2ba698c7106ed6d7b42bd64b4237",
        "initiators": [
          "https://www.datadoghq-browser-agent.com/datadog-rum.js",
          "https://ui.powerreviews.com/tag-builds/10309/4.1/js/chunks/engine.js",
          "https://ui.powerreviews.com/tag-builds/10309/4.1/js/chunks/623.js",
          "https://ui.powerreviews.com/tag-builds/10309/4.1/js/chunks/category-snippet.js"
        ],
        "time": 0.1721959999995306
      },
      {
        "url": "https://t.powerreviews.com/t/v1.gif?e=rd&et=review-image-display-visible&id=5SkB6JFYsb&uid=HT-MONN0oa&t=kxgtwgc3&l=nl_NL&mgid=49021&mid=811778&pid=ALLIE&p=https%3A%2F%2Fwww.kipling.com%2Fnl-nl%2Fallie-black-mist-ki4363x4600-999.html&v=4.1&vv=10309",
        "method": "GET",
        "type": "Image",
        "referrerPolicy": "strict-origin-when-cross-origin",
        "referer": "https://www.kipling.com/",
        "status": 200,
        "size": 499,
        "remoteIPAddress": "13.227.219.49",
        "responseHeaders": {
          "etag": "\"fc94fb0c3ed8a8f909dbc7630a0987ff\""
        },
        "responseBodyHash": "10f9bfa42bb96c99729c9b2fee669803ad9c6fcd434d8d7d60a8dc8f5f7cc331",
        "initiators": [
          "https://ui.powerreviews.com/tag-builds/10309/4.1/js/chunks/engine.js",
          "https://ui.powerreviews.com/tag-builds/10309/4.1/js/chunks/review-display.js",
          "https://ui.powerreviews.com/tag-builds/10309/4.1/js/chunks/623.js"
        ],
        "time": 0.15416999999433756
      },
      {
        "url": "https://www.kipling.com/static/version1636522060/frontend/Vf/kipling/nl_NL/jquery/jquery.parsequery.min.js",
        "method": "GET",
        "type": "Script",
        "referrerPolicy": "strict-origin-when-cross-origin",
        "referer": "https://www.kipling.com/nl-nl/allie-black-mist-ki4363x4600-999.html",
        "status": 200,
        "size": 534,
        "remoteIPAddress": "23.222.38.47",
        "responseHeaders": {
          "cache-control": "max-age=31536000, public",
          "etag": "W/\"618b60b4-307\"",
          "expires": "Sat, 17 Dec 2022 15:56:17 GMT"
        },
        "responseBodyHash": "74225a560596189508a4a14aa6d6ecad4bc6ba90de6e0b9d716a861ac220c640",
        "initiators": [
          "https://www.kipling.com/static/version1636522060/_cache/merged/33c3a92e596bcb0a6527f8461165bcad.min.js",
          "https://www.kipling.com/static/version1636522060/frontend/Vf/kipling/nl_NL/magepack/bundle-common.min.js"
        ],
        "time": 0.006061000021873042
      },
      {
        "url": "https://rum-collector-2.pingdom.net/img/beacon.gif?id=563b194fabe53de26084ec42&sAW=800&sAH=600&bIW=1440&bIH=812&pD=24&dPR=1&or=portrait-primary&nT=0&rC=0&nS=0&cS=14&cE=25&dLE=14&dLS=2&fS=0&hS=15&rE=-1&rS=-1&reS=25&resS=1729&resE=1732&uEE=-1&uES=-1&dL=1738&dI=2192&dCLES=2192&dCLEE=2194&dC=2584&lES=2584&lEE=2588&s=nt&title=ALLIE%20%7C%20Medium%20Etui%20met%20Ritssluiting%20%7C%20Kipling%20NL&path=https%3A%2F%2Fwww.kipling.com%2Fnl-nl%2Fallie-black-mist-ki4363x4600-999.html&ref=&sId=b02hjj6n&sST=1640134780&sIS=1&rV=0&v=1.4.1",
        "method": "GET",
        "type": "XHR",
        "referrerPolicy": "strict-origin-when-cross-origin",
        "referer": "https://www.kipling.com/",
        "status": 200,
        "size": 213,
        "remoteIPAddress": "52.214.198.134",
        "responseHeaders": {
          "access-control-allow-origin": "*",
          "cache-control": "no-cache, no-store, must-revalidate",
          "expires": "0",
          "pragma": "no-cache"
        },
        "responseBodyHash": "e3b0c44298fc1c149afbf4c8996fb92427ae41e4649b934ca495991b7852b855",
        "initiators": [
          "https://www.datadoghq-browser-agent.com/datadog-rum.js",
          "https://rum-static.pingdom.net/prum.min.js"
        ],
        "time": 0.0858159999770578
      },
      {
        "url": "https://geolocation.onetrust.com/cookieconsentpub/v1/geo/location",
        "method": "GET",
        "type": "Script",
        "referrerPolicy": "strict-origin-when-cross-origin",
        "referer": "https://www.kipling.com/",
        "status": 200,
        "size": 395,
        "remoteIPAddress": "104.20.184.68",
        "responseHeaders": {},
        "responseBodyHash": "b47fbb15b82c9c2b3099a23ec79c680183bc5aafe7c990cd1d11044331c4b4ce",
        "initiators": [
          "https://cdn.cookielaw.org/scripttemplates/otSDKStub.js"
        ],
        "time": 0.03679100002045743
      },
      {
        "url": "https://t.powerreviews.com/t/v1.gif?e=rd&id=LLy8gUkIxn&uid=HT-MONN0oa&t=kxgtwghq&l=nl_NL&mgid=49021&mid=811778&pid=ALLIE&p=https%3A%2F%2Fwww.kipling.com%2Fnl-nl%2Fallie-black-mist-ki4363x4600-999.html&v=4.1&vv=10309",
        "method": "GET",
        "type": "Image",
        "referrerPolicy": "strict-origin-when-cross-origin",
        "referer": "https://www.kipling.com/",
        "status": 200,
        "size": 499,
        "remoteIPAddress": "13.227.219.49",
        "responseHeaders": {
          "etag": "\"fc94fb0c3ed8a8f909dbc7630a0987ff\""
        },
        "responseBodyHash": "10f9bfa42bb96c99729c9b2fee669803ad9c6fcd434d8d7d60a8dc8f5f7cc331",
        "initiators": [
          "https://ui.powerreviews.com/tag-builds/10309/4.1/js/chunks/engine.js",
          "https://ui.powerreviews.com/tag-builds/10309/4.1/js/chunks/934.js",
          "https://ui.powerreviews.com/tag-builds/10309/4.1/js/chunks/623.js"
        ],
        "time": 0.582698000012897
      },
      {
        "url": "https://cdn.cookielaw.org/scripttemplates/6.27.0/otBannerSdk.js",
        "method": "GET",
        "type": "Script",
        "referrerPolicy": "strict-origin-when-cross-origin",
        "referer": "https://www.kipling.com/",
        "status": 200,
        "size": 78322,
        "remoteIPAddress": "104.16.148.64",
        "responseHeaders": {
          "access-control-allow-origin": "*",
          "cache-control": "max-age=14400",
          "etag": "0x8D9B37727F240FD"
        },
        "responseBodyHash": "a384d1fc7d84b2fe1b1cb470193838a86a5c72d39268aed7825e2235285b5ef7",
        "initiators": [
          "https://cdn.cookielaw.org/scripttemplates/otSDKStub.js"
        ],
        "time": 0.015921000012895092
      },
      {
        "url": "https://cdn.cookielaw.org/consent/f808bc0e-5a8f-451f-91ed-3101cec5e8e3/7a08cff2-124c-40dd-969f-5c3d9895c0ee/nl.json",
        "method": "GET",
        "type": "Fetch",
        "referrerPolicy": "strict-origin-when-cross-origin",
        "referer": "https://www.kipling.com/",
        "status": 200,
        "size": 13201,
        "remoteIPAddress": "104.16.148.64",
        "responseHeaders": {
          "access-control-allow-origin": "*",
          "cache-control": "public, max-age=14400",
          "etag": "0x8D9BEF695AD1E15",
          "expires": "Wed, 22 Dec 2021 04:59:41 GMT"
        },
        "responseBodyHash": "a9bc55e0fa304ea5ccc72588ea1e730d744acead972c8c741aab9822528fbaf3",
        "initiators": [
          "https://www.datadoghq-browser-agent.com/datadog-rum.js",
          "https://cdn.cookielaw.org/scripttemplates/6.27.0/otBannerSdk.js"
        ],
        "time": 0.029395999998087063
      },
      {
        "url": "https://cdn.cookielaw.org/scripttemplates/6.27.0/assets/otCenterRounded.json",
        "method": "GET",
        "type": "Fetch",
        "referrerPolicy": "strict-origin-when-cross-origin",
        "referer": "https://www.kipling.com/",
        "status": 200,
        "size": 2742,
        "remoteIPAddress": "104.16.148.64",
        "responseHeaders": {
          "access-control-allow-origin": "*",
          "cache-control": "max-age=14400",
          "etag": "0x8D9B377229DA3A2"
        },
        "responseBodyHash": "b26a37736a1c5a3e268b492a0b89a278c88208bdf6ea88543c0720c0317854c8",
        "initiators": [
          "https://www.datadoghq-browser-agent.com/datadog-rum.js",
          "https://cdn.cookielaw.org/scripttemplates/6.27.0/otBannerSdk.js"
        ],
        "time": 0.012939000007463619
      },
      {
        "url": "https://cdn.cookielaw.org/scripttemplates/6.27.0/assets/v2/otPcCenter.json",
        "method": "GET",
        "type": "Fetch",
        "referrerPolicy": "strict-origin-when-cross-origin",
        "referer": "https://www.kipling.com/",
        "status": 200,
        "size": 11923,
        "remoteIPAddress": "104.16.148.64",
        "responseHeaders": {
          "access-control-allow-origin": "*",
          "cache-control": "max-age=14400",
          "etag": "0x8D9B377239B4147"
        },
        "responseBodyHash": "e365f91028edea76d06d71cbf54c82fd62dcb673357f1a282149bcefdd04e41d",
        "initiators": [
          "https://www.datadoghq-browser-agent.com/datadog-rum.js",
          "https://cdn.cookielaw.org/scripttemplates/6.27.0/otBannerSdk.js"
        ],
        "time": 0.009747999982209876
      },
      {
        "url": "https://cdn.cookielaw.org/scripttemplates/6.27.0/assets/otCommonStyles.css",
        "method": "GET",
        "type": "Fetch",
        "referrerPolicy": "strict-origin-when-cross-origin",
        "referer": "https://www.kipling.com/",
        "status": 200,
        "size": 4402,
        "remoteIPAddress": "104.16.148.64",
        "responseHeaders": {
          "access-control-allow-origin": "*",
          "cache-control": "max-age=14400"
        },
        "responseBodyHash": "2ee6fdf3d0f4d826380054030e5a9fd6fc8c451d9fe28123f1d76e632332e659",
        "initiators": [
          "https://www.datadoghq-browser-agent.com/datadog-rum.js",
          "https://cdn.cookielaw.org/scripttemplates/6.27.0/otBannerSdk.js"
        ],
        "time": 0.010772000008728355
      },
      {
        "url": "https://cdn.cookielaw.org/logos/a835895b-feb8-40f2-8164-ad61ce73ded7/785a40db-4265-4222-9cd6-dc0b26fea93a/logo_kp.png",
        "method": "GET",
        "type": "Image",
        "referrerPolicy": "strict-origin-when-cross-origin",
        "referer": "https://www.kipling.com/",
        "status": 200,
        "size": 4665,
        "remoteIPAddress": "104.16.148.64",
        "responseHeaders": {
          "access-control-allow-origin": "*",
          "cache-control": "max-age=14400",
          "etag": "0x8D7E5E003C9A3F7"
        },
        "responseBodyHash": "fa1b55d77cb8b5dd329258b14e49e8f47aeca3e4d2767e2edea1e57e2bc5d0a8",
        "initiators": [],
        "time": 0.013249000010546297
      },
      {
        "url": "https://cdn.cookielaw.org/logos/static/poweredBy_ot_logo.svg",
        "method": "GET",
        "type": "Image",
        "referrerPolicy": "strict-origin-when-cross-origin",
        "referer": "https://www.kipling.com/",
        "status": 200,
        "size": 1692,
        "remoteIPAddress": "104.16.148.64",
        "responseHeaders": {
          "access-control-allow-origin": "*",
          "cache-control": "max-age=14400"
        },
        "responseBodyHash": "49b9b4996d1ff0a8e3de643a0c623255bf631f298f2799b949c29de93926ee7a",
        "initiators": [],
        "time": 0.03431099999579601
      },
      {
        "url": "https://privacyportal-eu.onetrust.com/request/v1/consentreceipts",
        "method": "OPTIONS",
        "type": "Preflight",
        "referrerPolicy": "strict-origin-when-cross-origin",
        "status": 200,
        "size": 0,
        "remoteIPAddress": "104.20.185.68",
        "responseHeaders": {
          "access-control-allow-origin": "*"
        },
        "responseBodyHash": null,
        "initiators": [
          "https://privacyportal-eu.onetrust.com/request/v1/consentreceipts"
        ],
        "time": 0.047495000006165355
      },
      {
        "url": "https://privacyportal-eu.onetrust.com/request/v1/consentreceipts",
        "method": "POST",
        "type": "XHR",
        "referrerPolicy": "strict-origin-when-cross-origin",
        "referer": "https://www.kipling.com/",
        "status": 200,
        "size": 1509,
        "remoteIPAddress": "104.20.185.68",
        "responseHeaders": {
          "access-control-allow-origin": "*"
        },
        "responseBodyHash": "0cce37ad9811eda2c63bdbd2b99c8200c94606882cb34fc64c8ef32026cd4c39",
        "initiators": [
          "https://www.datadoghq-browser-agent.com/datadog-rum.js",
          "https://cdn.cookielaw.org/scripttemplates/6.27.0/otBannerSdk.js",
          "__puppeteer_evaluation_script__"
        ],
        "time": 0.10947800002759323
      }
    ]
  }
}